Workbook
Name CALCULUS: Dashboard2[]
Name SegmentaçãodeDados_Meses__Data: #N/A
Name SegmentaçãodeDados_Tipo_Fluxo: #N/A

Sheet DB_MOVIMENTACAO
A1: ID_Transacao | B1: Data | C1: Tipo Fluxo | D1: ID Entidade | E1: Nome da Entidade | F1: ID Produto | G1: Descrição do Produto | H1: Quantidade | I1: Valor Unitário | J1: Valor Total | K1: Status Financeiro | L1: Status Logistico | M1: Previsão de Entrega | O1: Atualização randômica para as movimentações com ID entre T0021 a T1020
A2: T0001 | B2: 45658 | C2: Saida | D2: CLI005 | E2: =IF(Tabela_Movimentacao_Geral[[#This Row],[Tipo Fluxo]]="Saida",_xlfn.XLOOKUP(Tabela_Movimentacao_Geral[[#This Row],[ID Entidade]], Tabela_Clientes[ID_Cliente],Tabela_Clientes[Nome_Cliente],"Cliente não encontrado"),_xlfn.XLOOKUP(Tabela_Movimentacao_Geral[[#This Row],[ID Entidade]], Tabela_Fornecedores[ID_Fornecedor], Tabela_Fornecedores[Nome_Fantasia], "Fornecedor não encontrado")) -> Banco Futuro | F2: PROD006 | G2: =_xlfn.XLOOKUP(Tabela_Movimentacao_Geral[[#This Row],[ID Produto]], Tabela_Produtos[ID_Produto],Tabela_Produtos[Descricao_Produto],"Produto não encontrado") -> Notebook i7 16GB 512GB SSD | H2: 2 | I2: =_xlfn.XLOOKUP(Tabela_Movimentacao_Geral[[#This Row],[ID Produto]], Tabela_Produtos[ID_Produto],Tabela_Produtos[Preco_Unitario_Venda]) -> 5500 | J2: =Tabela_Movimentacao_Geral[[#This Row],[Quantidade]] * Tabela_Movimentacao_Geral[[#This Row],[Valor Unitário]] -> 11000 | K2: Pago | L2: Entregue | M2: =IF( $O$7="Desbloqueado", IF( Tabela_Movimentacao_Geral[[#This Row],[Tipo Fluxo]]="Entrada", Tabela_Movimentacao_Geral[[#This Row],[Data]] + _xlfn.XLOOKUP(Tabela_Movimentacao_Geral[[#This Row],[ID Entidade]],Tabela_Fornecedores[ID_Fornecedor],Tabela_Fornecedores[Lead_Time]), "N/A" ), Tabela_Movimentacao_Geral[[#This Row],[Previsão de Entrega]] ) -> N/A
A3: T0002 | B3: 45659 | C3: Entrada | D3: FORN001 | E3: =IF(Tabela_Movimentacao_Geral[[#This Row],[Tipo Fluxo]]="Saida",_xlfn.XLOOKUP(Tabela_Movimentacao_Geral[[#This Row],[ID Entidade]], Tabela_Clientes[ID_Cliente],Tabela_Clientes[Nome_Cliente],"Cliente não encontrado"),_xlfn.XLOOKUP(Tabela_Movimentacao_Geral[[#This Row],[ID Entidade]], Tabela_Fornecedores[ID_Fornecedor], Tabela_Fornecedores[Nome_Fantasia], "Fornecedor não encontrado")) -> TechFlow Solucoes | F3: PROD001 | G3: =_xlfn.XLOOKUP(Tabela_Movimentacao_Geral[[#This Row],[ID Produto]], Tabela_Produtos[ID_Produto],Tabela_Produtos[Descricao_Produto],"Produto não encontrado") -> Monitor 24 pol Full HD | H3: 10 | I3: =_xlfn.XLOOKUP(Tabela_Movimentacao_Geral[[#This Row],[ID Produto]], Tabela_Produtos[ID_Produto],Tabela_Produtos[Preco_Unitario_Venda]) -> 850 | J3: =Tabela_Movimentacao_Geral[[#This Row],[Quantidade]] * Tabela_Movimentacao_Geral[[#This Row],[Valor Unitário]] -> 8500 | K3: Pendente | L3: Aguardando | M3: =IF( $O$7="Desbloqueado", IF( Tabela_Movimentacao_Geral[[#This Row],[Tipo Fluxo]]="Entrada", Tabela_Movimentacao_Geral[[#This Row],[Data]] + _xlfn.XLOOKUP(Tabela_Movimentacao_Geral[[#This Row],[ID Entidade]],Tabela_Fornecedores[ID_Fornecedor],Tabela_Fornecedores[Lead_Time]), "N/A" ), Tabela_Movimentacao_Geral[[#This Row],[Previsão de Entrega]] ) -> 45664
A4: T0003 | B4: 45660 | C4: Saida | D4: CLI001 | E4: =IF(Tabela_Movimentacao_Geral[[#This Row],[Tipo Fluxo]]="Saida",_xlfn.XLOOKUP(Tabela_Movimentacao_Geral[[#This Row],[ID Entidade]], Tabela_Clientes[ID_Cliente],Tabela_Clientes[Nome_Cliente],"Cliente não encontrado"),_xlfn.XLOOKUP(Tabela_Movimentacao_Geral[[#This Row],[ID Entidade]], Tabela_Fornecedores[ID_Fornecedor], Tabela_Fornecedores[Nome_Fantasia], "Fornecedor não encontrado")) -> Industrias Alpha | F4: PROD005 | G4: =_xlfn.XLOOKUP(Tabela_Movimentacao_Geral[[#This Row],[ID Produto]], Tabela_Produtos[ID_Produto],Tabela_Produtos[Descricao_Produto],"Produto não encontrado") -> Notebook i5 8GB 256GB SSD | H4: 1 | I4: =_xlfn.XLOOKUP(Tabela_Movimentacao_Geral[[#This Row],[ID Produto]], Tabela_Produtos[ID_Produto],Tabela_Produtos[Preco_Unitario_Venda]) -> 3500 | J4: =Tabela_Movimentacao_Geral[[#This Row],[Quantidade]] * Tabela_Movimentacao_Geral[[#This Row],[Valor Unitário]] -> 3500 | K4: Atrasado | L4: Entregue | M4: =IF( $O$7="Desbloqueado", IF( Tabela_Movimentacao_Geral[[#This Row],[Tipo Fluxo]]="Entrada", Tabela_Movimentacao_Geral[[#This Row],[Data]] + _xlfn.XLOOKUP(Tabela_Movimentacao_Geral[[#This Row],[ID Entidade]],Tabela_Fornecedores[ID_Fornecedor],Tabela_Fornecedores[Lead_Time]), "N/A" ), Tabela_Movimentacao_Geral[[#This Row],[Previsão de Entrega]] ) -> N/A
A5: T0004 | B5: 45661 | C5: Saida | D5: CLI020 | E5: =IF(Tabela_Movimentacao_Geral[[#This Row],[Tipo Fluxo]]="Saida",_xlfn.XLOOKUP(Tabela_Movimentacao_Geral[[#This Row],[ID Entidade]], Tabela_Clientes[ID_Cliente],Tabela_Clientes[Nome_Cliente],"Cliente não encontrado"),_xlfn.XLOOKUP(Tabela_Movimentacao_Geral[[#This Row],[ID Entidade]], Tabela_Fornecedores[ID_Fornecedor], Tabela_Fornecedores[Nome_Fantasia], "Fornecedor não encontrado")) -> Oficina Mecanica | F5: PROD003 | G5: =_xlfn.XLOOKUP(Tabela_Movimentacao_Geral[[#This Row],[ID Produto]], Tabela_Produtos[ID_Produto],Tabela_Produtos[Descricao_Produto],"Produto não encontrado") -> Mouse Sem Fio Optico | H5: 5 | I5: =_xlfn.XLOOKUP(Tabela_Movimentacao_Geral[[#This Row],[ID Produto]], Tabela_Produtos[ID_Produto],Tabela_Produtos[Preco_Unitario_Venda]) -> 120 | J5: =Tabela_Movimentacao_Geral[[#This Row],[Quantidade]] * Tabela_Movimentacao_Geral[[#This Row],[Valor Unitário]] -> 600 | K5: Pago | L5: Em Rota | M5: =IF( $O$7="Desbloqueado", IF( Tabela_Movimentacao_Geral[[#This Row],[Tipo Fluxo]]="Entrada", Tabela_Movimentacao_Geral[[#This Row],[Data]] + _xlfn.XLOOKUP(Tabela_Movimentacao_Geral[[#This Row],[ID Entidade]],Tabela_Fornecedores[ID_Fornecedor],Tabela_Fornecedores[Lead_Time]), "N/A" ), Tabela_Movimentacao_Geral[[#This Row],[Previsão de Entrega]] ) -> N/A
A6: T0005 | B6: 45662 | C6: Entrada | D6: FORN008 | E6: =IF(Tabela_Movimentacao_Geral[[#This Row],[Tipo Fluxo]]="Saida",_xlfn.XLOOKUP(Tabela_Movimentacao_Geral[[#This Row],[ID Entidade]], Tabela_Clientes[ID_Cliente],Tabela_Clientes[Nome_Cliente],"Cliente não encontrado"),_xlfn.XLOOKUP(Tabela_Movimentacao_Geral[[#This Row],[ID Entidade]], Tabela_Fornecedores[ID_Fornecedor], Tabela_Fornecedores[Nome_Fantasia], "Fornecedor não encontrado")) -> Global Chips | F6: PROD010 | G6: =_xlfn.XLOOKUP(Tabela_Movimentacao_Geral[[#This Row],[ID Produto]], Tabela_Produtos[ID_Produto],Tabela_Produtos[Descricao_Produto],"Produto não encontrado") -> SSD 480GB SATA3 | H6: 50 | I6: =_xlfn.XLOOKUP(Tabela_Movimentacao_Geral[[#This Row],[ID Produto]], Tabela_Produtos[ID_Produto],Tabela_Produtos[Preco_Unitario_Venda]) -> 320 | J6: =Tabela_Movimentacao_Geral[[#This Row],[Quantidade]] * Tabela_Movimentacao_Geral[[#This Row],[Valor Unitário]] -> 16000 | K6: Pago | L6: Entregue | M6: =IF( $O$7="Desbloqueado", IF( Tabela_Movimentacao_Geral[[#This Row],[Tipo Fluxo]]="Entrada", Tabela_Movimentacao_Geral[[#This Row],[Data]] + _xlfn.XLOOKUP(Tabela_Movimentacao_Geral[[#This Row],[ID Entidade]],Tabela_Fornecedores[ID_Fornecedor],Tabela_Fornecedores[Lead_Time]), "N/A" ), Tabela_Movimentacao_Geral[[#This Row],[Previsão de Entrega]] ) -> 45677
A7: T0006 | B7: 45663 | C7: Saida | D7: CLI010 | E7: =IF(Tabela_Movimentacao_Geral[[#This Row],[Tipo Fluxo]]="Saida",_xlfn.XLOOKUP(Tabela_Movimentacao_Geral[[#This Row],[ID Entidade]], Tabela_Clientes[ID_Cliente],Tabela_Clientes[Nome_Cliente],"Cliente não encontrado"),_xlfn.XLOOKUP(Tabela_Movimentacao_Geral[[#This Row],[ID Entidade]], Tabela_Fornecedores[ID_Fornecedor], Tabela_Fornecedores[Nome_Fantasia], "Fornecedor não encontrado")) -> Hotel Estrela | F7: PROD042 | G7: =_xlfn.XLOOKUP(Tabela_Movimentacao_Geral[[#This Row],[ID Produto]], Tabela_Produtos[ID_Produto],Tabela_Produtos[Descricao_Produto],"Produto não encontrado") -> Docking Station Universal | H7: 1 | I7: =_xlfn.XLOOKUP(Tabela_Movimentacao_Geral[[#This Row],[ID Produto]], Tabela_Produtos[ID_Produto],Tabela_Produtos[Preco_Unitario_Venda]) -> 890 | J7: =Tabela_Movimentacao_Geral[[#This Row],[Quantidade]] * Tabela_Movimentacao_Geral[[#This Row],[Valor Unitário]] -> 890 | K7: Pago | L7: Entregue | M7: =IF( $O$7="Desbloqueado", IF( Tabela_Movimentacao_Geral[[#This Row],[Tipo Fluxo]]="Entrada", Tabela_Movimentacao_Geral[[#This Row],[Data]] + _xlfn.XLOOKUP(Tabela_Movimentacao_Geral[[#This Row],[ID Entidade]],Tabela_Fornecedores[ID_Fornecedor],Tabela_Fornecedores[Lead_Time]), "N/A" ), Tabela_Movimentacao_Geral[[#This Row],[Previsão de Entrega]] ) -> N/A | O7: Bloqueado
A8: T0007 | B8: 45664 | C8: Entrada | D8: FORN015 | E8: =IF(Tabela_Movimentacao_Geral[[#This Row],[Tipo Fluxo]]="Saida",_xlfn.XLOOKUP(Tabela_Movimentacao_Geral[[#This Row],[ID Entidade]], Tabela_Clientes[ID_Cliente],Tabela_Clientes[Nome_Cliente],"Cliente não encontrado"),_xlfn.XLOOKUP(Tabela_Movimentacao_Geral[[#This Row],[ID Entidade]], Tabela_Fornecedores[ID_Fornecedor], Tabela_Fornecedores[Nome_Fantasia], "Fornecedor não encontrado")) -> Print Smart | F8: PROD051 | G8: =_xlfn.XLOOKUP(Tabela_Movimentacao_Geral[[#This Row],[ID Produto]], Tabela_Produtos[ID_Produto],Tabela_Produtos[Descricao_Produto],"Produto não encontrado") -> Papel A4 Report 500fls | H8: 100 | I8: =_xlfn.XLOOKUP(Tabela_Movimentacao_Geral[[#This Row],[ID Produto]], Tabela_Produtos[ID_Produto],Tabela_Produtos[Preco_Unitario_Venda]) -> 28 | J8: =Tabela_Movimentacao_Geral[[#This Row],[Quantidade]] * Tabela_Movimentacao_Geral[[#This Row],[Valor Unitário]] -> 2800 | K8: Pendente | L8: Aguardando | M8: =IF( $O$7="Desbloqueado", IF( Tabela_Movimentacao_Geral[[#This Row],[Tipo Fluxo]]="Entrada", Tabela_Movimentacao_Geral[[#This Row],[Data]] + _xlfn.XLOOKUP(Tabela_Movimentacao_Geral[[#This Row],[ID Entidade]],Tabela_Fornecedores[ID_Fornecedor],Tabela_Fornecedores[Lead_Time]), "N/A" ), Tabela_Movimentacao_Geral[[#This Row],[Previsão de Entrega]] ) -> 45667
A9: T0008 | B9: 45665 | C9: Saida | D9: CLI003 | E9: =IF(Tabela_Movimentacao_Geral[[#This Row],[Tipo Fluxo]]="Saida",_xlfn.XLOOKUP(Tabela_Movimentacao_Geral[[#This Row],[ID Entidade]], Tabela_Clientes[ID_Cliente],Tabela_Clientes[Nome_Cliente],"Cliente não encontrado"),_xlfn.XLOOKUP(Tabela_Movimentacao_Geral[[#This Row],[ID Entidade]], Tabela_Fornecedores[ID_Fornecedor], Tabela_Fornecedores[Nome_Fantasia], "Fornecedor não encontrado")) -> Hospital Vida | F9: PROD106 | G9: =_xlfn.XLOOKUP(Tabela_Movimentacao_Geral[[#This Row],[ID Produto]], Tabela_Produtos[ID_Produto],Tabela_Produtos[Descricao_Produto],"Produto não encontrado") -> MacBook Air M2 13p | H9: 1 | I9: =_xlfn.XLOOKUP(Tabela_Movimentacao_Geral[[#This Row],[ID Produto]], Tabela_Produtos[ID_Produto],Tabela_Produtos[Preco_Unitario_Venda]) -> 9500 | J9: =Tabela_Movimentacao_Geral[[#This Row],[Quantidade]] * Tabela_Movimentacao_Geral[[#This Row],[Valor Unitário]] -> 9500 | K9: Pago | L9: Em Rota | M9: =IF( $O$7="Desbloqueado", IF( Tabela_Movimentacao_Geral[[#This Row],[Tipo Fluxo]]="Entrada", Tabela_Movimentacao_Geral[[#This Row],[Data]] + _xlfn.XLOOKUP(Tabela_Movimentacao_Geral[[#This Row],[ID Entidade]],Tabela_Fornecedores[ID_Fornecedor],Tabela_Fornecedores[Lead_Time]), "N/A" ), Tabela_Movimentacao_Geral[[#This Row],[Previsão de Entrega]] ) -> N/A | O9: Manter Bloqueado para atualizar o Dashbard!
A10: T0009 | B10: 45666 | C10: Saida | D10: CLI015 | E10: =IF(Tabela_Movimentacao_Geral[[#This Row],[Tipo Fluxo]]="Saida",_xlfn.XLOOKUP(Tabela_Movimentacao_Geral[[#This Row],[ID Entidade]], Tabela_Clientes[ID_Cliente],Tabela_Clientes[Nome_Cliente],"Cliente não encontrado"),_xlfn.XLOOKUP(Tabela_Movimentacao_Geral[[#This Row],[ID Entidade]], Tabela_Fornecedores[ID_Fornecedor], Tabela_Fornecedores[Nome_Fantasia], "Fornecedor não encontrado")) -> Pet Shop Amigo | F10: PROD012 | G10: =_xlfn.XLOOKUP(Tabela_Movimentacao_Geral[[#This Row],[ID Produto]], Tabela_Produtos[ID_Produto],Tabela_Produtos[Descricao_Produto],"Produto não encontrado") -> Webcam 1080p Business | H10: 3 | I10: =_xlfn.XLOOKUP(Tabela_Movimentacao_Geral[[#This Row],[ID Produto]], Tabela_Produtos[ID_Produto],Tabela_Produtos[Preco_Unitario_Venda]) -> 450 | J10: =Tabela_Movimentacao_Geral[[#This Row],[Quantidade]] * Tabela_Movimentacao_Geral[[#This Row],[Valor Unitário]] -> 1350 | K10: Atrasado | L10: Aguardando | M10: =IF( $O$7="Desbloqueado", IF( Tabela_Movimentacao_Geral[[#This Row],[Tipo Fluxo]]="Entrada", Tabela_Movimentacao_Geral[[#This Row],[Data]] + _xlfn.XLOOKUP(Tabela_Movimentacao_Geral[[#This Row],[ID Entidade]],Tabela_Fornecedores[ID_Fornecedor],Tabela_Fornecedores[Lead_Time]), "N/A" ), Tabela_Movimentacao_Geral[[#This Row],[Previsão de Entrega]] ) -> N/A
A11: T0010 | B11: 45667 | C11: Entrada | D11: FORN020 | E11: =IF(Tabela_Movimentacao_Geral[[#This Row],[Tipo Fluxo]]="Saida",_xlfn.XLOOKUP(Tabela_Movimentacao_Geral[[#This Row],[ID Entidade]], Tabela_Clientes[ID_Cliente],Tabela_Clientes[Nome_Cliente],"Cliente não encontrado"),_xlfn.XLOOKUP(Tabela_Movimentacao_Geral[[#This Row],[ID Entidade]], Tabela_Fornecedores[ID_Fornecedor], Tabela_Fornecedores[Nome_Fantasia], "Fornecedor não encontrado")) -> AI Systems | F11: PROD121 | G11: =_xlfn.XLOOKUP(Tabela_Movimentacao_Geral[[#This Row],[ID Produto]], Tabela_Produtos[ID_Produto],Tabela_Produtos[Descricao_Produto],"Produto não encontrado") -> Licenca SQL Server Standard | H11: 1 | I11: =_xlfn.XLOOKUP(Tabela_Movimentacao_Geral[[#This Row],[ID Produto]], Tabela_Produtos[ID_Produto],Tabela_Produtos[Preco_Unitario_Venda]) -> 15000 | J11: =Tabela_Movimentacao_Geral[[#This Row],[Quantidade]] * Tabela_Movimentacao_Geral[[#This Row],[Valor Unitário]] -> 15000 | K11: Pago | L11: Entregue | M11: =IF( $O$7="Desbloqueado", IF( Tabela_Movimentacao_Geral[[#This Row],[Tipo Fluxo]]="Entrada", Tabela_Movimentacao_Geral[[#This Row],[Data]] + _xlfn.XLOOKUP(Tabela_Movimentacao_Geral[[#This Row],[ID Entidade]],Tabela_Fornecedores[ID_Fornecedor],Tabela_Fornecedores[Lead_Time]), "N/A" ), Tabela_Movimentacao_Geral[[#This Row],[Previsão de Entrega]] ) -> 45668
A12: T0011 | B12: 45668 | C12: Saida | D12: CLI007 | E12: =IF(Tabela_Movimentacao_Geral[[#This Row],[Tipo Fluxo]]="Saida",_xlfn.XLOOKUP(Tabela_Movimentacao_Geral[[#This Row],[ID Entidade]], Tabela_Clientes[ID_Cliente],Tabela_Clientes[Nome_Cliente],"Cliente não encontrado"),_xlfn.XLOOKUP(Tabela_Movimentacao_Geral[[#This Row],[ID Entidade]], Tabela_Fornecedores[ID_Fornecedor], Tabela_Fornecedores[Nome_Fantasia], "Fornecedor não encontrado")) -> Tecno Logica | F12: PROD002 | G12: =_xlfn.XLOOKUP(Tabela_Movimentacao_Geral[[#This Row],[ID Produto]], Tabela_Produtos[ID_Produto],Tabela_Produtos[Descricao_Produto],"Produto não encontrado") -> Teclado Mecanico RGB | H12: 4 | I12: =_xlfn.XLOOKUP(Tabela_Movimentacao_Geral[[#This Row],[ID Produto]], Tabela_Produtos[ID_Produto],Tabela_Produtos[Preco_Unitario_Venda]) -> 350 | J12: =Tabela_Movimentacao_Geral[[#This Row],[Quantidade]] * Tabela_Movimentacao_Geral[[#This Row],[Valor Unitário]] -> 1400 | K12: Pendente | L12: Em Rota | M12: =IF( $O$7="Desbloqueado", IF( Tabela_Movimentacao_Geral[[#This Row],[Tipo Fluxo]]="Entrada", Tabela_Movimentacao_Geral[[#This Row],[Data]] + _xlfn.XLOOKUP(Tabela_Movimentacao_Geral[[#This Row],[ID Entidade]],Tabela_Fornecedores[ID_Fornecedor],Tabela_Fornecedores[Lead_Time]), "N/A" ), Tabela_Movimentacao_Geral[[#This Row],[Previsão de Entrega]] ) -> N/A
A13: T0012 | B13: 45669 | C13: Saida | D13: CLI009 | E13: =IF(Tabela_Movimentacao_Geral[[#This Row],[Tipo Fluxo]]="Saida",_xlfn.XLOOKUP(Tabela_Movimentacao_Geral[[#This Row],[ID Entidade]], Tabela_Clientes[ID_Cliente],Tabela_Clientes[Nome_Cliente],"Cliente não encontrado"),_xlfn.XLOOKUP(Tabela_Movimentacao_Geral[[#This Row],[ID Entidade]], Tabela_Fornecedores[ID_Fornecedor], Tabela_Fornecedores[Nome_Fantasia], "Fornecedor não encontrado")) -> Farma Plus | F13: PROD085 | G13: =_xlfn.XLOOKUP(Tabela_Movimentacao_Geral[[#This Row],[ID Produto]], Tabela_Produtos[ID_Produto],Tabela_Produtos[Descricao_Produto],"Produto não encontrado") -> Cabo Optico Patch Cord 3m | H13: 20 | I13: =_xlfn.XLOOKUP(Tabela_Movimentacao_Geral[[#This Row],[ID Produto]], Tabela_Produtos[ID_Produto],Tabela_Produtos[Preco_Unitario_Venda]) -> 85 | J13: =Tabela_Movimentacao_Geral[[#This Row],[Quantidade]] * Tabela_Movimentacao_Geral[[#This Row],[Valor Unitário]] -> 1700 | K13: Pago | L13: Entregue | M13: =IF( $O$7="Desbloqueado", IF( Tabela_Movimentacao_Geral[[#This Row],[Tipo Fluxo]]="Entrada", Tabela_Movimentacao_Geral[[#This Row],[Data]] + _xlfn.XLOOKUP(Tabela_Movimentacao_Geral[[#This Row],[ID Entidade]],Tabela_Fornecedores[ID_Fornecedor],Tabela_Fornecedores[Lead_Time]), "N/A" ), Tabela_Movimentacao_Geral[[#This Row],[Previsão de Entrega]] ) -> N/A
A14: T0013 | B14: 45670 | C14: Entrada | D14: FORN002 | E14: =IF(Tabela_Movimentacao_Geral[[#This Row],[Tipo Fluxo]]="Saida",_xlfn.XLOOKUP(Tabela_Movimentacao_Geral[[#This Row],[ID Entidade]], Tabela_Clientes[ID_Cliente],Tabela_Clientes[Nome_Cliente],"Cliente não encontrado"),_xlfn.XLOOKUP(Tabela_Movimentacao_Geral[[#This Row],[ID Entidade]], Tabela_Fornecedores[ID_Fornecedor], Tabela_Fornecedores[Nome_Fantasia], "Fornecedor não encontrado")) -> SoftPrime Licencas | F14: PROD022 | G14: =_xlfn.XLOOKUP(Tabela_Movimentacao_Geral[[#This Row],[ID Produto]], Tabela_Produtos[ID_Produto],Tabela_Produtos[Descricao_Produto],"Produto não encontrado") -> Licenca Windows 11 Pro | H14: 10 | I14: =_xlfn.XLOOKUP(Tabela_Movimentacao_Geral[[#This Row],[ID Produto]], Tabela_Produtos[ID_Produto],Tabela_Produtos[Preco_Unitario_Venda]) -> 980 | J14: =Tabela_Movimentacao_Geral[[#This Row],[Quantidade]] * Tabela_Movimentacao_Geral[[#This Row],[Valor Unitário]] -> 9800 | K14: Pago | L14: Entregue | M14: =IF( $O$7="Desbloqueado", IF( Tabela_Movimentacao_Geral[[#This Row],[Tipo Fluxo]]="Entrada", Tabela_Movimentacao_Geral[[#This Row],[Data]] + _xlfn.XLOOKUP(Tabela_Movimentacao_Geral[[#This Row],[ID Entidade]],Tabela_Fornecedores[ID_Fornecedor],Tabela_Fornecedores[Lead_Time]), "N/A" ), Tabela_Movimentacao_Geral[[#This Row],[Previsão de Entrega]] ) -> 45671
A15: T0014 | B15: 45671 | C15: Saida | D15: CLI018 | E15: =IF(Tabela_Movimentacao_Geral[[#This Row],[Tipo Fluxo]]="Saida",_xlfn.XLOOKUP(Tabela_Movimentacao_Geral[[#This Row],[ID Entidade]], Tabela_Clientes[ID_Cliente],Tabela_Clientes[Nome_Cliente],"Cliente não encontrado"),_xlfn.XLOOKUP(Tabela_Movimentacao_Geral[[#This Row],[ID Entidade]], Tabela_Fornecedores[ID_Fornecedor], Tabela_Fornecedores[Nome_Fantasia], "Fornecedor não encontrado")) -> Clinica Sorriso | F15: PROD113 | G15: =_xlfn.XLOOKUP(Tabela_Movimentacao_Geral[[#This Row],[ID Produto]], Tabela_Produtos[ID_Produto],Tabela_Produtos[Descricao_Produto],"Produto não encontrado") -> Headphone Bluetooth NoiseC | H15: 2 | I15: =_xlfn.XLOOKUP(Tabela_Movimentacao_Geral[[#This Row],[ID Produto]], Tabela_Produtos[ID_Produto],Tabela_Produtos[Preco_Unitario_Venda]) -> 950 | J15: =Tabela_Movimentacao_Geral[[#This Row],[Quantidade]] * Tabela_Movimentacao_Geral[[#This Row],[Valor Unitário]] -> 1900 | K15: Pendente | L15: Em Rota | M15: =IF( $O$7="Desbloqueado", IF( Tabela_Movimentacao_Geral[[#This Row],[Tipo Fluxo]]="Entrada", Tabela_Movimentacao_Geral[[#This Row],[Data]] + _xlfn.XLOOKUP(Tabela_Movimentacao_Geral[[#This Row],[ID Entidade]],Tabela_Fornecedores[ID_Fornecedor],Tabela_Fornecedores[Lead_Time]), "N/A" ), Tabela_Movimentacao_Geral[[#This Row],[Previsão de Entrega]] ) -> N/A
A16: T0015 | B16: 45672 | C16: Saida | D16: CLI002 | E16: =IF(Tabela_Movimentacao_Geral[[#This Row],[Tipo Fluxo]]="Saida",_xlfn.XLOOKUP(Tabela_Movimentacao_Geral[[#This Row],[ID Entidade]], Tabela_Clientes[ID_Cliente],Tabela_Clientes[Nome_Cliente],"Cliente não encontrado"),_xlfn.XLOOKUP(Tabela_Movimentacao_Geral[[#This Row],[ID Entidade]], Tabela_Fornecedores[ID_Fornecedor], Tabela_Fornecedores[Nome_Fantasia], "Fornecedor não encontrado")) -> Varejo Total | F16: PROD033 | G16: =_xlfn.XLOOKUP(Tabela_Movimentacao_Geral[[#This Row],[ID Produto]], Tabela_Produtos[ID_Produto],Tabela_Produtos[Descricao_Produto],"Produto não encontrado") -> Pendrive 64GB USB 3.1 | H16: 15 | I16: =_xlfn.XLOOKUP(Tabela_Movimentacao_Geral[[#This Row],[ID Produto]], Tabela_Produtos[ID_Produto],Tabela_Produtos[Preco_Unitario_Venda]) -> 65 | J16: =Tabela_Movimentacao_Geral[[#This Row],[Quantidade]] * Tabela_Movimentacao_Geral[[#This Row],[Valor Unitário]] -> 975 | K16: Pago | L16: Entregue | M16: =IF( $O$7="Desbloqueado", IF( Tabela_Movimentacao_Geral[[#This Row],[Tipo Fluxo]]="Entrada", Tabela_Movimentacao_Geral[[#This Row],[Data]] + _xlfn.XLOOKUP(Tabela_Movimentacao_Geral[[#This Row],[ID Entidade]],Tabela_Fornecedores[ID_Fornecedor],Tabela_Fornecedores[Lead_Time]), "N/A" ), Tabela_Movimentacao_Geral[[#This Row],[Previsão de Entrega]] ) -> N/A
A17: T0016 | B17: 45673 | C17: Entrada | D17: FORN011 | E17: =IF(Tabela_Movimentacao_Geral[[#This Row],[Tipo Fluxo]]="Saida",_xlfn.XLOOKUP(Tabela_Movimentacao_Geral[[#This Row],[ID Entidade]], Tabela_Clientes[ID_Cliente],Tabela_Clientes[Nome_Cliente],"Cliente não encontrado"),_xlfn.XLOOKUP(Tabela_Movimentacao_Geral[[#This Row],[ID Entidade]], Tabela_Fornecedores[ID_Fornecedor], Tabela_Fornecedores[Nome_Fantasia], "Fornecedor não encontrado")) -> Energy Solution | F17: PROD131 | G17: =_xlfn.XLOOKUP(Tabela_Movimentacao_Geral[[#This Row],[ID Produto]], Tabela_Produtos[ID_Produto],Tabela_Produtos[Descricao_Produto],"Produto não encontrado") -> Bateria Nobreak 12V 7Ah | H17: 5 | I17: =_xlfn.XLOOKUP(Tabela_Movimentacao_Geral[[#This Row],[ID Produto]], Tabela_Produtos[ID_Produto],Tabela_Produtos[Preco_Unitario_Venda]) -> 145 | J17: =Tabela_Movimentacao_Geral[[#This Row],[Quantidade]] * Tabela_Movimentacao_Geral[[#This Row],[Valor Unitário]] -> 725 | K17: Atrasado | L17: Aguardando | M17: =IF( $O$7="Desbloqueado", IF( Tabela_Movimentacao_Geral[[#This Row],[Tipo Fluxo]]="Entrada", Tabela_Movimentacao_Geral[[#This Row],[Data]] + _xlfn.XLOOKUP(Tabela_Movimentacao_Geral[[#This Row],[ID Entidade]],Tabela_Fornecedores[ID_Fornecedor],Tabela_Fornecedores[Lead_Time]), "N/A" ), Tabela_Movimentacao_Geral[[#This Row],[Previsão de Entrega]] ) -> 45677 | O17: Ctrl + Alt + F5 (Atualiza todas as conexões e tabelas do arquivo de uma vez só).
A18: T0017 | B18: 45674 | C18: Saida | D18: CLI004 | E18: =IF(Tabela_Movimentacao_Geral[[#This Row],[Tipo Fluxo]]="Saida",_xlfn.XLOOKUP(Tabela_Movimentacao_Geral[[#This Row],[ID Entidade]], Tabela_Clientes[ID_Cliente],Tabela_Clientes[Nome_Cliente],"Cliente não encontrado"),_xlfn.XLOOKUP(Tabela_Movimentacao_Geral[[#This Row],[ID Entidade]], Tabela_Fornecedores[ID_Fornecedor], Tabela_Fornecedores[Nome_Fantasia], "Fornecedor não encontrado")) -> Escola Saber | F18: PROD009 | G18: =_xlfn.XLOOKUP(Tabela_Movimentacao_Geral[[#This Row],[ID Produto]], Tabela_Produtos[ID_Produto],Tabela_Produtos[Descricao_Produto],"Produto não encontrado") -> Cabo HDMI 2.0 2m | H18: 30 | I18: =_xlfn.XLOOKUP(Tabela_Movimentacao_Geral[[#This Row],[ID Produto]], Tabela_Produtos[ID_Produto],Tabela_Produtos[Preco_Unitario_Venda]) -> 45 | J18: =Tabela_Movimentacao_Geral[[#This Row],[Quantidade]] * Tabela_Movimentacao_Geral[[#This Row],[Valor Unitário]] -> 1350 | K18: Pago | L18: Entregue | M18: =IF( $O$7="Desbloqueado", IF( Tabela_Movimentacao_Geral[[#This Row],[Tipo Fluxo]]="Entrada", Tabela_Movimentacao_Geral[[#This Row],[Data]] + _xlfn.XLOOKUP(Tabela_Movimentacao_Geral[[#This Row],[ID Entidade]],Tabela_Fornecedores[ID_Fornecedor],Tabela_Fornecedores[Lead_Time]), "N/A" ), Tabela_Movimentacao_Geral[[#This Row],[Previsão de Entrega]] ) -> N/A
A19: T0018 | B19: 45675 | C19: Entrada | D19: FORN005 | E19: =IF(Tabela_Movimentacao_Geral[[#This Row],[Tipo Fluxo]]="Saida",_xlfn.XLOOKUP(Tabela_Movimentacao_Geral[[#This Row],[ID Entidade]], Tabela_Clientes[ID_Cliente],Tabela_Clientes[Nome_Cliente],"Cliente não encontrado"),_xlfn.XLOOKUP(Tabela_Movimentacao_Geral[[#This Row],[ID Entidade]], Tabela_Fornecedores[ID_Fornecedor], Tabela_Fornecedores[Nome_Fantasia], "Fornecedor não encontrado")) -> CloudNexus Data | F19: PROD189 | G19: =_xlfn.XLOOKUP(Tabela_Movimentacao_Geral[[#This Row],[ID Produto]], Tabela_Produtos[ID_Produto],Tabela_Produtos[Descricao_Produto],"Produto não encontrado") -> Switch Core Layer 3 | H19: 1 | I19: =_xlfn.XLOOKUP(Tabela_Movimentacao_Geral[[#This Row],[ID Produto]], Tabela_Produtos[ID_Produto],Tabela_Produtos[Preco_Unitario_Venda]) -> 22000 | J19: =Tabela_Movimentacao_Geral[[#This Row],[Quantidade]] * Tabela_Movimentacao_Geral[[#This Row],[Valor Unitário]] -> 22000 | K19: Pago | L19: Entregue | M19: =IF( $O$7="Desbloqueado", IF( Tabela_Movimentacao_Geral[[#This Row],[Tipo Fluxo]]="Entrada", Tabela_Movimentacao_Geral[[#This Row],[Data]] + _xlfn.XLOOKUP(Tabela_Movimentacao_Geral[[#This Row],[ID Entidade]],Tabela_Fornecedores[ID_Fornecedor],Tabela_Fornecedores[Lead_Time]), "N/A" ), Tabela_Movimentacao_Geral[[#This Row],[Previsão de Entrega]] ) -> 45676
A20: T0019 | B20: 45676 | C20: Saida | D20: CLI012 | E20: =IF(Tabela_Movimentacao_Geral[[#This Row],[Tipo Fluxo]]="Saida",_xlfn.XLOOKUP(Tabela_Movimentacao_Geral[[#This Row],[ID Entidade]], Tabela_Clientes[ID_Cliente],Tabela_Clientes[Nome_Cliente],"Cliente não encontrado"),_xlfn.XLOOKUP(Tabela_Movimentacao_Geral[[#This Row],[ID Entidade]], Tabela_Fornecedores[ID_Fornecedor], Tabela_Fornecedores[Nome_Fantasia], "Fornecedor não encontrado")) -> Padaria Real | F20: PROD007 | G20: =_xlfn.XLOOKUP(Tabela_Movimentacao_Geral[[#This Row],[ID Produto]], Tabela_Produtos[ID_Produto],Tabela_Produtos[Descricao_Produto],"Produto não encontrado") -> Impressora Laser Color | H20: 1 | I20: =_xlfn.XLOOKUP(Tabela_Movimentacao_Geral[[#This Row],[ID Produto]], Tabela_Produtos[ID_Produto],Tabela_Produtos[Preco_Unitario_Venda]) -> 1800 | J20: =Tabela_Movimentacao_Geral[[#This Row],[Quantidade]] * Tabela_Movimentacao_Geral[[#This Row],[Valor Unitário]] -> 1800 | K20: Pago | L20: Em Rota | M20: =IF( $O$7="Desbloqueado", IF( Tabela_Movimentacao_Geral[[#This Row],[Tipo Fluxo]]="Entrada", Tabela_Movimentacao_Geral[[#This Row],[Data]] + _xlfn.XLOOKUP(Tabela_Movimentacao_Geral[[#This Row],[ID Entidade]],Tabela_Fornecedores[ID_Fornecedor],Tabela_Fornecedores[Lead_Time]), "N/A" ), Tabela_Movimentacao_Geral[[#This Row],[Previsão de Entrega]] ) -> N/A
A21: T0020 | B21: 45677 | C21: Saida | D21: CLI008 | E21: =IF(Tabela_Movimentacao_Geral[[#This Row],[Tipo Fluxo]]="Saida",_xlfn.XLOOKUP(Tabela_Movimentacao_Geral[[#This Row],[ID Entidade]], Tabela_Clientes[ID_Cliente],Tabela_Clientes[Nome_Cliente],"Cliente não encontrado"),_xlfn.XLOOKUP(Tabela_Movimentacao_Geral[[#This Row],[ID Entidade]], Tabela_Fornecedores[ID_Fornecedor], Tabela_Fornecedores[Nome_Fantasia], "Fornecedor não encontrado")) -> Supermercado Sol | F21: PROD018 | G21: =_xlfn.XLOOKUP(Tabela_Movimentacao_Geral[[#This Row],[ID Produto]], Tabela_Produtos[ID_Produto],Tabela_Produtos[Descricao_Produto],"Produto não encontrado") -> HD Externo 1TB | H21: 5 | I21: =_xlfn.XLOOKUP(Tabela_Movimentacao_Geral[[#This Row],[ID Produto]], Tabela_Produtos[ID_Produto],Tabela_Produtos[Preco_Unitario_Venda]) -> 380 | J21: =Tabela_Movimentacao_Geral[[#This Row],[Quantidade]] * Tabela_Movimentacao_Geral[[#This Row],[Valor Unitário]] -> 1900 | K21: Pendente | L21: Entregue | M21: =IF( $O$7="Desbloqueado", IF( Tabela_Movimentacao_Geral[[#This Row],[Tipo Fluxo]]="Entrada", Tabela_Movimentacao_Geral[[#This Row],[Data]] + _xlfn.XLOOKUP(Tabela_Movimentacao_Geral[[#This Row],[ID Entidade]],Tabela_Fornecedores[ID_Fornecedor],Tabela_Fornecedores[Lead_Time]), "N/A" ), Tabela_Movimentacao_Geral[[#This Row],[Previsão de Entrega]] ) -> N/A
A22: ="T"&TEXT(ROW(A22)-1,"0000") -> T0021 | B22: 45677 | C22: {=IF($O$7="Desbloqueado", _xlfn.LET( _xlpm.saldo_atual, SUM(($C$2:$C21="Entrada")*($F$2:$F21=Tabela_Movimentacao_Geral[[#This Row],[ID Produto]])*($H$2:$H21) - ($C$2:$C21="Saida")*($F$2:$F21=Tabela_Movimentacao_Geral[[#This Row],[ID Produto]])*($H$2:$H21)), IF(_xlpm.saldo_atual > 0, IF(RANDBETWEEN(0,10)>3,"Saida","Entrada"), "Entrada") ), Tabela_Movimentacao_Geral[[#This Row],[Tipo Fluxo]] )} -> Entrada | D22: =IF( $O$7="Desbloqueado", IF( Tabela_Movimentacao_Geral[[#This Row],[Tipo Fluxo]]="Saida", "CLI"&TEXT(RANDBETWEEN(1,20),"000"), "FORN"&TEXT(RANDBETWEEN(1,20),"000") ), Tabela_Movimentacao_Geral[[#This Row],[ID Entidade]] ) -> FORN004 | E22: =IF(Tabela_Movimentacao_Geral[[#This Row],[Tipo Fluxo]]="Saida",_xlfn.XLOOKUP(Tabela_Movimentacao_Geral[[#This Row],[ID Entidade]], Tabela_Clientes[ID_Cliente],Tabela_Clientes[Nome_Cliente],"Cliente não encontrado"),_xlfn.XLOOKUP(Tabela_Movimentacao_Geral[[#This Row],[ID Entidade]], Tabela_Fornecedores[ID_Fornecedor], Tabela_Fornecedores[Nome_Fantasia], "Fornecedor não encontrado")) -> LogiBrasil Transportes | F22: =IF( $O$7="Desbloqueado", "PROD"&TEXT(RANDBETWEEN(1,200),"000"), Tabela_Movimentacao_Geral[[#This Row],[ID Produto]] ) -> PROD195 | G22: =_xlfn.XLOOKUP(Tabela_Movimentacao_Geral[[#This Row],[ID Produto]], Tabela_Produtos[ID_Produto],Tabela_Produtos[Descricao_Produto],"Produto não encontrado") -> Terminador Optico | H22: {=IF( $O$7="Desbloqueado", _xlfn.LET( _xlpm.saldo_atual, SUM(($C$2:$C21="Entrada")*($F$2:$F21=Tabela_Movimentacao_Geral[[#This Row],[ID Produto]])*($H$2:$H21) - ($C$2:$C21="Saida")*($F$2:$F21=Tabela_Movimentacao_Geral[[#This Row],[ID Produto]])*($H$2:$H21)), _xlpm.estoque_minimo, _xlfn.XLOOKUP(Tabela_Movimentacao_Geral[[#This Row],[ID Produto]], Tabela_Produtos[ID_Produto], Tabela_Produtos[Estoque_Minimo], 0), IF( _xlpm.saldo_atual > _xlpm.estoque_minimo, IF( Tabela_Movimentacao_Geral[[#This Row],[Tipo Fluxo]]="Saida", RANDBETWEEN(1, _xlpm.saldo_atual), RANDBETWEEN(1, 100) ), IF( Tabela_Movimentacao_Geral[[#This Row],[Tipo Fluxo]]="Saida", RANDBETWEEN(1, _xlpm.saldo_atual), IF( _xlpm.saldo_atual < 0, ABS(_xlpm.saldo_atual) + _xlpm.estoque_minimo + RANDBETWEEN(1, 100), _xlpm.estoque_minimo - _xlpm.saldo_atual + RANDBETWEEN(1, 100) ) ) ) ), Tabela_Movimentacao_Geral[[#This Row],[Quantidade]] )} -> 29 | I22: =_xlfn.XLOOKUP(Tabela_Movimentacao_Geral[[#This Row],[ID Produto]], Tabela_Produtos[ID_Produto],Tabela_Produtos[Preco_Unitario_Venda]) -> 120 | J22: =Tabela_Movimentacao_Geral[[#This Row],[Quantidade]] * Tabela_Movimentacao_Geral[[#This Row],[Valor Unitário]] -> 3480 | K22: =IF( $O$7="Desbloqueado", CHOOSE(RANDBETWEEN(1,3),"Pago","Pendente","Atrasado"), Tabela_Movimentacao_Geral[[#This Row],[Status Financeiro]] ) -> Atrasado | L22: =IF( $O$7="Desbloqueado", CHOOSE(RANDBETWEEN(1,3),"Entregue","Em Rota","Aguardando"), Tabela_Movimentacao_Geral[[#This Row],[Status Logistico]] ) -> Em Rota | M22: =IF( $O$7="Desbloqueado", IF( Tabela_Movimentacao_Geral[[#This Row],[Tipo Fluxo]]="Entrada", Tabela_Movimentacao_Geral[[#This Row],[Data]] + _xlfn.XLOOKUP(Tabela_Movimentacao_Geral[[#This Row],[ID Entidade]],Tabela_Fornecedores[ID_Fornecedor],Tabela_Fornecedores[Lead_Time]), "N/A" ), Tabela_Movimentacao_Geral[[#This Row],[Previsão de Entrega]] ) -> 0
A23: ="T"&TEXT(ROW(A23)-1,"0000") -> T0022 | B23: 45677 | C23: {=IF($O$7="Desbloqueado", _xlfn.LET( _xlpm.saldo_atual, SUM(($C$2:$C22="Entrada")*($F$2:$F22=Tabela_Movimentacao_Geral[[#This Row],[ID Produto]])*($H$2:$H22) - ($C$2:$C22="Saida")*($F$2:$F22=Tabela_Movimentacao_Geral[[#This Row],[ID Produto]])*($H$2:$H22)), IF(_xlpm.saldo_atual > 0, IF(RANDBETWEEN(0,10)>3,"Saida","Entrada"), "Entrada") ), Tabela_Movimentacao_Geral[[#This Row],[Tipo Fluxo]] )} -> Entrada | D23: =IF( $O$7="Desbloqueado", IF( Tabela_Movimentacao_Geral[[#This Row],[Tipo Fluxo]]="Saida", "CLI"&TEXT(RANDBETWEEN(1,20),"000"), "FORN"&TEXT(RANDBETWEEN(1,20),"000") ), Tabela_Movimentacao_Geral[[#This Row],[ID Entidade]] ) -> FORN007 | E23: =IF(Tabela_Movimentacao_Geral[[#This Row],[Tipo Fluxo]]="Saida",_xlfn.XLOOKUP(Tabela_Movimentacao_Geral[[#This Row],[ID Entidade]], Tabela_Clientes[ID_Cliente],Tabela_Clientes[Nome_Cliente],"Cliente não encontrado"),_xlfn.XLOOKUP(Tabela_Movimentacao_Geral[[#This Row],[ID Entidade]], Tabela_Fornecedores[ID_Fornecedor], Tabela_Fornecedores[Nome_Fantasia], "Fornecedor não encontrado")) -> CyberSecurity SA | F23: =IF( $O$7="Desbloqueado", "PROD"&TEXT(RANDBETWEEN(1,200),"000"), Tabela_Movimentacao_Geral[[#This Row],[ID Produto]] ) -> PROD157 | G23: =_xlfn.XLOOKUP(Tabela_Movimentacao_Geral[[#This Row],[ID Produto]], Tabela_Produtos[ID_Produto],Tabela_Produtos[Descricao_Produto],"Produto não encontrado") -> Fita Dupla Face 3M | H23: {=IF( $O$7="Desbloqueado", _xlfn.LET( _xlpm.saldo_atual, SUM(($C$2:$C22="Entrada")*($F$2:$F22=Tabela_Movimentacao_Geral[[#This Row],[ID Produto]])*($H$2:$H22) - ($C$2:$C22="Saida")*($F$2:$F22=Tabela_Movimentacao_Geral[[#This Row],[ID Produto]])*($H$2:$H22)), _xlpm.estoque_minimo, _xlfn.XLOOKUP(Tabela_Movimentacao_Geral[[#This Row],[ID Produto]], Tabela_Produtos[ID_Produto], Tabela_Produtos[Estoque_Minimo], 0), IF( _xlpm.saldo_atual > _xlpm.estoque_minimo, IF( Tabela_Movimentacao_Geral[[#This Row],[Tipo Fluxo]]="Saida", RANDBETWEEN(1, _xlpm.saldo_atual), RANDBETWEEN(1, 100) ), IF( Tabela_Movimentacao_Geral[[#This Row],[Tipo Fluxo]]="Saida", RANDBETWEEN(1, _xlpm.saldo_atual), IF( _xlpm.saldo_atual < 0, ABS(_xlpm.saldo_atual) + _xlpm.estoque_minimo + RANDBETWEEN(1, 100), _xlpm.estoque_minimo - _xlpm.saldo_atual + RANDBETWEEN(1, 100) ) ) ) ), Tabela_Movimentacao_Geral[[#This Row],[Quantidade]] )} -> 95 | I23: =_xlfn.XLOOKUP(Tabela_Movimentacao_Geral[[#This Row],[ID Produto]], Tabela_Produtos[ID_Produto],Tabela_Produtos[Preco_Unitario_Venda]) -> 28 | J23: =Tabela_Movimentacao_Geral[[#This Row],[Quantidade]] * Tabela_Movimentacao_Geral[[#This Row],[Valor Unitário]] -> 2660 | K23: =IF( $O$7="Desbloqueado", CHOOSE(RANDBETWEEN(1,3),"Pago","Pendente","Atrasado"), Tabela_Movimentacao_Geral[[#This Row],[Status Financeiro]] ) -> Pendente | L23: =IF( $O$7="Desbloqueado", CHOOSE(RANDBETWEEN(1,3),"Entregue","Em Rota","Aguardando"), Tabela_Movimentacao_Geral[[#This Row],[Status Logistico]] ) -> Entregue | M23: =IF( $O$7="Desbloqueado", IF( Tabela_Movimentacao_Geral[[#This Row],[Tipo Fluxo]]="Entrada", Tabela_Movimentacao_Geral[[#This Row],[Data]] + _xlfn.XLOOKUP(Tabela_Movimentacao_Geral[[#This Row],[ID Entidade]],Tabela_Fornecedores[ID_Fornecedor],Tabela_Fornecedores[Lead_Time]), "N/A" ), Tabela_Movimentacao_Geral[[#This Row],[Previsão de Entrega]] ) -> 45684
A24: ="T"&TEXT(ROW(A24)-1,"0000") -> T0023 | B24: 45677 | C24: {=IF($O$7="Desbloqueado", _xlfn.LET( _xlpm.saldo_atual, SUM(($C$2:$C23="Entrada")*($F$2:$F23=Tabela_Movimentacao_Geral[[#This Row],[ID Produto]])*($H$2:$H23) - ($C$2:$C23="Saida")*($F$2:$F23=Tabela_Movimentacao_Geral[[#This Row],[ID Produto]])*($H$2:$H23)), IF(_xlpm.saldo_atual > 0, IF(RANDBETWEEN(0,10)>3,"Saida","Entrada"), "Entrada") ), Tabela_Movimentacao_Geral[[#This Row],[Tipo Fluxo]] )} -> Entrada | D24: =IF( $O$7="Desbloqueado", IF( Tabela_Movimentacao_Geral[[#This Row],[Tipo Fluxo]]="Saida", "CLI"&TEXT(RANDBETWEEN(1,20),"000"), "FORN"&TEXT(RANDBETWEEN(1,20),"000") ), Tabela_Movimentacao_Geral[[#This Row],[ID Entidade]] ) -> FORN001 | E24: =IF(Tabela_Movimentacao_Geral[[#This Row],[Tipo Fluxo]]="Saida",_xlfn.XLOOKUP(Tabela_Movimentacao_Geral[[#This Row],[ID Entidade]], Tabela_Clientes[ID_Cliente],Tabela_Clientes[Nome_Cliente],"Cliente não encontrado"),_xlfn.XLOOKUP(Tabela_Movimentacao_Geral[[#This Row],[ID Entidade]], Tabela_Fornecedores[ID_Fornecedor], Tabela_Fornecedores[Nome_Fantasia], "Fornecedor não encontrado")) -> TechFlow Solucoes | F24: =IF( $O$7="Desbloqueado", "PROD"&TEXT(RANDBETWEEN(1,200),"000"), Tabela_Movimentacao_Geral[[#This Row],[ID Produto]] ) -> PROD074 | G24: =_xlfn.XLOOKUP(Tabela_Movimentacao_Geral[[#This Row],[ID Produto]], Tabela_Produtos[ID_Produto],Tabela_Produtos[Descricao_Produto],"Produto não encontrado") -> Cordao para Cracha | H24: {=IF( $O$7="Desbloqueado", _xlfn.LET( _xlpm.saldo_atual, SUM(($C$2:$C23="Entrada")*($F$2:$F23=Tabela_Movimentacao_Geral[[#This Row],[ID Produto]])*($H$2:$H23) - ($C$2:$C23="Saida")*($F$2:$F23=Tabela_Movimentacao_Geral[[#This Row],[ID Produto]])*($H$2:$H23)), _xlpm.estoque_minimo, _xlfn.XLOOKUP(Tabela_Movimentacao_Geral[[#This Row],[ID Produto]], Tabela_Produtos[ID_Produto], Tabela_Produtos[Estoque_Minimo], 0), IF( _xlpm.saldo_atual > _xlpm.estoque_minimo, IF( Tabela_Movimentacao_Geral[[#This Row],[Tipo Fluxo]]="Saida", RANDBETWEEN(1, _xlpm.saldo_atual), RANDBETWEEN(1, 100) ), IF( Tabela_Movimentacao_Geral[[#This Row],[Tipo Fluxo]]="Saida", RANDBETWEEN(1, _xlpm.saldo_atual), IF( _xlpm.saldo_atual < 0, ABS(_xlpm.saldo_atual) + _xlpm.estoque_minimo + RANDBETWEEN(1, 100), _xlpm.estoque_minimo - _xlpm.saldo_atual + RANDBETWEEN(1, 100) ) ) ) ), Tabela_Movimentacao_Geral[[#This Row],[Quantidade]] )} -> 372 | I24: =_xlfn.XLOOKUP(Tabela_Movimentacao_Geral[[#This Row],[ID Produto]], Tabela_Produtos[ID_Produto],Tabela_Produtos[Preco_Unitario_Venda]) -> 3.5 | J24: =Tabela_Movimentacao_Geral[[#This Row],[Quantidade]] * Tabela_Movimentacao_Geral[[#This Row],[Valor Unitário]] -> 1302 | K24: =IF( $O$7="Desbloqueado", CHOOSE(RANDBETWEEN(1,3),"Pago","Pendente","Atrasado"), Tabela_Movimentacao_Geral[[#This Row],[Status Financeiro]] ) -> Pago | L24: =IF( $O$7="Desbloqueado", CHOOSE(RANDBETWEEN(1,3),"Entregue","Em Rota","Aguardando"), Tabela_Movimentacao_Geral[[#This Row],[Status Logistico]] ) -> Em Rota | M24: =IF( $O$7="Desbloqueado", IF( Tabela_Movimentacao_Geral[[#This Row],[Tipo Fluxo]]="Entrada", Tabela_Movimentacao_Geral[[#This Row],[Data]] + _xlfn.XLOOKUP(Tabela_Movimentacao_Geral[[#This Row],[ID Entidade]],Tabela_Fornecedores[ID_Fornecedor],Tabela_Fornecedores[Lead_Time]), "N/A" ), Tabela_Movimentacao_Geral[[#This Row],[Previsão de Entrega]] ) -> 45682
A25: ="T"&TEXT(ROW(A25)-1,"0000") -> T0024 | B25: 45678 | C25: {=IF($O$7="Desbloqueado", _xlfn.LET( _xlpm.saldo_atual, SUM(($C$2:$C24="Entrada")*($F$2:$F24=Tabela_Movimentacao_Geral[[#This Row],[ID Produto]])*($H$2:$H24) - ($C$2:$C24="Saida")*($F$2:$F24=Tabela_Movimentacao_Geral[[#This Row],[ID Produto]])*($H$2:$H24)), IF(_xlpm.saldo_atual > 0, IF(RANDBETWEEN(0,10)>3,"Saida","Entrada"), "Entrada") ), Tabela_Movimentacao_Geral[[#This Row],[Tipo Fluxo]] )} -> Entrada | D25: =IF( $O$7="Desbloqueado", IF( Tabela_Movimentacao_Geral[[#This Row],[Tipo Fluxo]]="Saida", "CLI"&TEXT(RANDBETWEEN(1,20),"000"), "FORN"&TEXT(RANDBETWEEN(1,20),"000") ), Tabela_Movimentacao_Geral[[#This Row],[ID Entidade]] ) -> FORN009 | E25: =IF(Tabela_Movimentacao_Geral[[#This Row],[Tipo Fluxo]]="Saida",_xlfn.XLOOKUP(Tabela_Movimentacao_Geral[[#This Row],[ID Entidade]], Tabela_Clientes[ID_Cliente],Tabela_Clientes[Nome_Cliente],"Cliente não encontrado"),_xlfn.XLOOKUP(Tabela_Movimentacao_Geral[[#This Row],[ID Entidade]], Tabela_Fornecedores[ID_Fornecedor], Tabela_Fornecedores[Nome_Fantasia], "Fornecedor não encontrado")) -> Movel Tech | F25: =IF( $O$7="Desbloqueado", "PROD"&TEXT(RANDBETWEEN(1,200),"000"), Tabela_Movimentacao_Geral[[#This Row],[ID Produto]] ) -> PROD175 | G25: =_xlfn.XLOOKUP(Tabela_Movimentacao_Geral[[#This Row],[ID Produto]], Tabela_Produtos[ID_Produto],Tabela_Produtos[Descricao_Produto],"Produto não encontrado") -> Plastico Bolha 1.2x50m | H25: {=IF( $O$7="Desbloqueado", _xlfn.LET( _xlpm.saldo_atual, SUM(($C$2:$C24="Entrada")*($F$2:$F24=Tabela_Movimentacao_Geral[[#This Row],[ID Produto]])*($H$2:$H24) - ($C$2:$C24="Saida")*($F$2:$F24=Tabela_Movimentacao_Geral[[#This Row],[ID Produto]])*($H$2:$H24)), _xlpm.estoque_minimo, _xlfn.XLOOKUP(Tabela_Movimentacao_Geral[[#This Row],[ID Produto]], Tabela_Produtos[ID_Produto], Tabela_Produtos[Estoque_Minimo], 0), IF( _xlpm.saldo_atual > _xlpm.estoque_minimo, IF( Tabela_Movimentacao_Geral[[#This Row],[Tipo Fluxo]]="Saida", RANDBETWEEN(1, _xlpm.saldo_atual), RANDBETWEEN(1, 100) ), IF( Tabela_Movimentacao_Geral[[#This Row],[Tipo Fluxo]]="Saida", RANDBETWEEN(1, _xlpm.saldo_atual), IF( _xlpm.saldo_atual < 0, ABS(_xlpm.saldo_atual) + _xlpm.estoque_minimo + RANDBETWEEN(1, 100), _xlpm.estoque_minimo - _xlpm.saldo_atual + RANDBETWEEN(1, 100) ) ) ) ), Tabela_Movimentacao_Geral[[#This Row],[Quantidade]] )} -> 99 | I25: =_xlfn.XLOOKUP(Tabela_Movimentacao_Geral[[#This Row],[ID Produto]], Tabela_Produtos[ID_Produto],Tabela_Produtos[Preco_Unitario_Venda]) -> 110 | J25: =Tabela_Movimentacao_Geral[[#This Row],[Quantidade]] * Tabela_Movimentacao_Geral[[#This Row],[Valor Unitário]] -> 10890 | K25: =IF( $O$7="Desbloqueado", CHOOSE(RANDBETWEEN(1,3),"Pago","Pendente","Atrasado"), Tabela_Movimentacao_Geral[[#This Row],[Status Financeiro]] ) -> Pago | L25: =IF( $O$7="Desbloqueado", CHOOSE(RANDBETWEEN(1,3),"Entregue","Em Rota","Aguardando"), Tabela_Movimentacao_Geral[[#This Row],[Status Logistico]] ) -> Em Rota | M25: =IF( $O$7="Desbloqueado", IF( Tabela_Movimentacao_Geral[[#This Row],[Tipo Fluxo]]="Entrada", Tabela_Movimentacao_Geral[[#This Row],[Data]] + _xlfn.XLOOKUP(Tabela_Movimentacao_Geral[[#This Row],[ID Entidade]],Tabela_Fornecedores[ID_Fornecedor],Tabela_Fornecedores[Lead_Time]), "N/A" ), Tabela_Movimentacao_Geral[[#This Row],[Previsão de Entrega]] ) -> 45688
A26: ="T"&TEXT(ROW(A26)-1,"0000") -> T0025 | B26: 45679 | C26: {=IF($O$7="Desbloqueado", _xlfn.LET( _xlpm.saldo_atual, SUM(($C$2:$C25="Entrada")*($F$2:$F25=Tabela_Movimentacao_Geral[[#This Row],[ID Produto]])*($H$2:$H25) - ($C$2:$C25="Saida")*($F$2:$F25=Tabela_Movimentacao_Geral[[#This Row],[ID Produto]])*($H$2:$H25)), IF(_xlpm.saldo_atual > 0, IF(RANDBETWEEN(0,10)>3,"Saida","Entrada"), "Entrada") ), Tabela_Movimentacao_Geral[[#This Row],[Tipo Fluxo]] )} -> Entrada | D26: =IF( $O$7="Desbloqueado", IF( Tabela_Movimentacao_Geral[[#This Row],[Tipo Fluxo]]="Saida", "CLI"&TEXT(RANDBETWEEN(1,20),"000"), "FORN"&TEXT(RANDBETWEEN(1,20),"000") ), Tabela_Movimentacao_Geral[[#This Row],[ID Entidade]] ) -> FORN001 | E26: =IF(Tabela_Movimentacao_Geral[[#This Row],[Tipo Fluxo]]="Saida",_xlfn.XLOOKUP(Tabela_Movimentacao_Geral[[#This Row],[ID Entidade]], Tabela_Clientes[ID_Cliente],Tabela_Clientes[Nome_Cliente],"Cliente não encontrado"),_xlfn.XLOOKUP(Tabela_Movimentacao_Geral[[#This Row],[ID Entidade]], Tabela_Fornecedores[ID_Fornecedor], Tabela_Fornecedores[Nome_Fantasia], "Fornecedor não encontrado")) -> TechFlow Solucoes | F26: =IF( $O$7="Desbloqueado", "PROD"&TEXT(RANDBETWEEN(1,200),"000"), Tabela_Movimentacao_Geral[[#This Row],[ID Produto]] ) -> PROD128 | G26: =_xlfn.XLOOKUP(Tabela_Movimentacao_Geral[[#This Row],[ID Produto]], Tabela_Produtos[ID_Produto],Tabela_Produtos[Descricao_Produto],"Produto não encontrado") -> Cabo de Rede Cat5e 5m | H26: {=IF( $O$7="Desbloqueado", _xlfn.LET( _xlpm.saldo_atual, SUM(($C$2:$C25="Entrada")*($F$2:$F25=Tabela_Movimentacao_Geral[[#This Row],[ID Produto]])*($H$2:$H25) - ($C$2:$C25="Saida")*($F$2:$F25=Tabela_Movimentacao_Geral[[#This Row],[ID Produto]])*($H$2:$H25)), _xlpm.estoque_minimo, _xlfn.XLOOKUP(Tabela_Movimentacao_Geral[[#This Row],[ID Produto]], Tabela_Produtos[ID_Produto], Tabela_Produtos[Estoque_Minimo], 0), IF( _xlpm.saldo_atual > _xlpm.estoque_minimo, IF( Tabela_Movimentacao_Geral[[#This Row],[Tipo Fluxo]]="Saida", RANDBETWEEN(1, _xlpm.saldo_atual), RANDBETWEEN(1, 100) ), IF( Tabela_Movimentacao_Geral[[#This Row],[Tipo Fluxo]]="Saida", RANDBETWEEN(1, _xlpm.saldo_atual), IF( _xlpm.saldo_atual < 0, ABS(_xlpm.saldo_atual) + _xlpm.estoque_minimo + RANDBETWEEN(1, 100), _xlpm.estoque_minimo - _xlpm.saldo_atual + RANDBETWEEN(1, 100) ) ) ) ), Tabela_Movimentacao_Geral[[#This Row],[Quantidade]] )} -> 179 | I26: =_xlfn.XLOOKUP(Tabela_Movimentacao_Geral[[#This Row],[ID Produto]], Tabela_Produtos[ID_Produto],Tabela_Produtos[Preco_Unitario_Venda]) -> 18 | J26: =Tabela_Movimentacao_Geral[[#This Row],[Quantidade]] * Tabela_Movimentacao_Geral[[#This Row],[Valor Unitário]] -> 3222 | K26: =IF( $O$7="Desbloqueado", CHOOSE(RANDBETWEEN(1,3),"Pago","Pendente","Atrasado"), Tabela_Movimentacao_Geral[[#This Row],[Status Financeiro]] ) -> Pendente | L26: =IF( $O$7="Desbloqueado", CHOOSE(RANDBETWEEN(1,3),"Entregue","Em Rota","Aguardando"), Tabela_Movimentacao_Geral[[#This Row],[Status Logistico]] ) -> Aguardando | M26: =IF( $O$7="Desbloqueado", IF( Tabela_Movimentacao_Geral[[#This Row],[Tipo Fluxo]]="Entrada", Tabela_Movimentacao_Geral[[#This Row],[Data]] + _xlfn.XLOOKUP(Tabela_Movimentacao_Geral[[#This Row],[ID Entidade]],Tabela_Fornecedores[ID_Fornecedor],Tabela_Fornecedores[Lead_Time]), "N/A" ), Tabela_Movimentacao_Geral[[#This Row],[Previsão de Entrega]] ) -> 45684
A27: ="T"&TEXT(ROW(A27)-1,"0000") -> T0026 | B27: 45679 | C27: {=IF($O$7="Desbloqueado", _xlfn.LET( _xlpm.saldo_atual, SUM(($C$2:$C26="Entrada")*($F$2:$F26=Tabela_Movimentacao_Geral[[#This Row],[ID Produto]])*($H$2:$H26) - ($C$2:$C26="Saida")*($F$2:$F26=Tabela_Movimentacao_Geral[[#This Row],[ID Produto]])*($H$2:$H26)), IF(_xlpm.saldo_atual > 0, IF(RANDBETWEEN(0,10)>3,"Saida","Entrada"), "Entrada") ), Tabela_Movimentacao_Geral[[#This Row],[Tipo Fluxo]] )} -> Entrada | D27: =IF( $O$7="Desbloqueado", IF( Tabela_Movimentacao_Geral[[#This Row],[Tipo Fluxo]]="Saida", "CLI"&TEXT(RANDBETWEEN(1,20),"000"), "FORN"&TEXT(RANDBETWEEN(1,20),"000") ), Tabela_Movimentacao_Geral[[#This Row],[ID Entidade]] ) -> FORN010 | E27: =IF(Tabela_Movimentacao_Geral[[#This Row],[Tipo Fluxo]]="Saida",_xlfn.XLOOKUP(Tabela_Movimentacao_Geral[[#This Row],[ID Entidade]], Tabela_Clientes[ID_Cliente],Tabela_Clientes[Nome_Cliente],"Cliente não encontrado"),_xlfn.XLOOKUP(Tabela_Movimentacao_Geral[[#This Row],[ID Entidade]], Tabela_Fornecedores[ID_Fornecedor], Tabela_Fornecedores[Nome_Fantasia], "Fornecedor não encontrado")) -> DataCenter Pro | F27: =IF( $O$7="Desbloqueado", "PROD"&TEXT(RANDBETWEEN(1,200),"000"), Tabela_Movimentacao_Geral[[#This Row],[ID Produto]] ) -> PROD135 | G27: =_xlfn.XLOOKUP(Tabela_Movimentacao_Geral[[#This Row],[ID Produto]], Tabela_Produtos[ID_Produto],Tabela_Produtos[Descricao_Produto],"Produto não encontrado") -> Ponteira Laser Apresentador | H27: {=IF( $O$7="Desbloqueado", _xlfn.LET( _xlpm.saldo_atual, SUM(($C$2:$C26="Entrada")*($F$2:$F26=Tabela_Movimentacao_Geral[[#This Row],[ID Produto]])*($H$2:$H26) - ($C$2:$C26="Saida")*($F$2:$F26=Tabela_Movimentacao_Geral[[#This Row],[ID Produto]])*($H$2:$H26)), _xlpm.estoque_minimo, _xlfn.XLOOKUP(Tabela_Movimentacao_Geral[[#This Row],[ID Produto]], Tabela_Produtos[ID_Produto], Tabela_Produtos[Estoque_Minimo], 0), IF( _xlpm.saldo_atual > _xlpm.estoque_minimo, IF( Tabela_Movimentacao_Geral[[#This Row],[Tipo Fluxo]]="Saida", RANDBETWEEN(1, _xlpm.saldo_atual), RANDBETWEEN(1, 100) ), IF( Tabela_Movimentacao_Geral[[#This Row],[Tipo Fluxo]]="Saida", RANDBETWEEN(1, _xlpm.saldo_atual), IF( _xlpm.saldo_atual < 0, ABS(_xlpm.saldo_atual) + _xlpm.estoque_minimo + RANDBETWEEN(1, 100), _xlpm.estoque_minimo - _xlpm.saldo_atual + RANDBETWEEN(1, 100) ) ) ) ), Tabela_Movimentacao_Geral[[#This Row],[Quantidade]] )} -> 42 | I27: =_xlfn.XLOOKUP(Tabela_Movimentacao_Geral[[#This Row],[ID Produto]], Tabela_Produtos[ID_Produto],Tabela_Produtos[Preco_Unitario_Venda]) -> 120 | J27: =Tabela_Movimentacao_Geral[[#This Row],[Quantidade]] * Tabela_Movimentacao_Geral[[#This Row],[Valor Unitário]] -> 5040 | K27: =IF( $O$7="Desbloqueado", CHOOSE(RANDBETWEEN(1,3),"Pago","Pendente","Atrasado"), Tabela_Movimentacao_Geral[[#This Row],[Status Financeiro]] ) -> Pago | L27: =IF( $O$7="Desbloqueado", CHOOSE(RANDBETWEEN(1,3),"Entregue","Em Rota","Aguardando"), Tabela_Movimentacao_Geral[[#This Row],[Status Logistico]] ) -> Em Rota | M27: =IF( $O$7="Desbloqueado", IF( Tabela_Movimentacao_Geral[[#This Row],[Tipo Fluxo]]="Entrada", Tabela_Movimentacao_Geral[[#This Row],[Data]] + _xlfn.XLOOKUP(Tabela_Movimentacao_Geral[[#This Row],[ID Entidade]],Tabela_Fornecedores[ID_Fornecedor],Tabela_Fornecedores[Lead_Time]), "N/A" ), Tabela_Movimentacao_Geral[[#This Row],[Previsão de Entrega]] ) -> 45681
A28: ="T"&TEXT(ROW(A28)-1,"0000") -> T0027 | B28: 45679 | C28: {=IF($O$7="Desbloqueado", _xlfn.LET( _xlpm.saldo_atual, SUM(($C$2:$C27="Entrada")*($F$2:$F27=Tabela_Movimentacao_Geral[[#This Row],[ID Produto]])*($H$2:$H27) - ($C$2:$C27="Saida")*($F$2:$F27=Tabela_Movimentacao_Geral[[#This Row],[ID Produto]])*($H$2:$H27)), IF(_xlpm.saldo_atual > 0, IF(RANDBETWEEN(0,10)>3,"Saida","Entrada"), "Entrada") ), Tabela_Movimentacao_Geral[[#This Row],[Tipo Fluxo]] )} -> Entrada | D28: =IF( $O$7="Desbloqueado", IF( Tabela_Movimentacao_Geral[[#This Row],[Tipo Fluxo]]="Saida", "CLI"&TEXT(RANDBETWEEN(1,20),"000"), "FORN"&TEXT(RANDBETWEEN(1,20),"000") ), Tabela_Movimentacao_Geral[[#This Row],[ID Entidade]] ) -> FORN008 | E28: =IF(Tabela_Movimentacao_Geral[[#This Row],[Tipo Fluxo]]="Saida",_xlfn.XLOOKUP(Tabela_Movimentacao_Geral[[#This Row],[ID Entidade]], Tabela_Clientes[ID_Cliente],Tabela_Clientes[Nome_Cliente],"Cliente não encontrado"),_xlfn.XLOOKUP(Tabela_Movimentacao_Geral[[#This Row],[ID Entidade]], Tabela_Fornecedores[ID_Fornecedor], Tabela_Fornecedores[Nome_Fantasia], "Fornecedor não encontrado")) -> Global Chips | F28: =IF( $O$7="Desbloqueado", "PROD"&TEXT(RANDBETWEEN(1,200),"000"), Tabela_Movimentacao_Geral[[#This Row],[ID Produto]] ) -> PROD150 | G28: =_xlfn.XLOOKUP(Tabela_Movimentacao_Geral[[#This Row],[ID Produto]], Tabela_Produtos[ID_Produto],Tabela_Produtos[Descricao_Produto],"Produto não encontrado") -> Lanterna de Led Inspeção | H28: {=IF( $O$7="Desbloqueado", _xlfn.LET( _xlpm.saldo_atual, SUM(($C$2:$C27="Entrada")*($F$2:$F27=Tabela_Movimentacao_Geral[[#This Row],[ID Produto]])*($H$2:$H27) - ($C$2:$C27="Saida")*($F$2:$F27=Tabela_Movimentacao_Geral[[#This Row],[ID Produto]])*($H$2:$H27)), _xlpm.estoque_minimo, _xlfn.XLOOKUP(Tabela_Movimentacao_Geral[[#This Row],[ID Produto]], Tabela_Produtos[ID_Produto], Tabela_Produtos[Estoque_Minimo], 0), IF( _xlpm.saldo_atual > _xlpm.estoque_minimo, IF( Tabela_Movimentacao_Geral[[#This Row],[Tipo Fluxo]]="Saida", RANDBETWEEN(1, _xlpm.saldo_atual), RANDBETWEEN(1, 100) ), IF( Tabela_Movimentacao_Geral[[#This Row],[Tipo Fluxo]]="Saida", RANDBETWEEN(1, _xlpm.saldo_atual), IF( _xlpm.saldo_atual < 0, ABS(_xlpm.saldo_atual) + _xlpm.estoque_minimo + RANDBETWEEN(1, 100), _xlpm.estoque_minimo - _xlpm.saldo_atual + RANDBETWEEN(1, 100) ) ) ) ), Tabela_Movimentacao_Geral[[#This Row],[Quantidade]] )} -> 73 | I28: =_xlfn.XLOOKUP(Tabela_Movimentacao_Geral[[#This Row],[ID Produto]], Tabela_Produtos[ID_Produto],Tabela_Produtos[Preco_Unitario_Venda]) -> 55 | J28: =Tabela_Movimentacao_Geral[[#This Row],[Quantidade]] * Tabela_Movimentacao_Geral[[#This Row],[Valor Unitário]] -> 4015 | K28: =IF( $O$7="Desbloqueado", CHOOSE(RANDBETWEEN(1,3),"Pago","Pendente","Atrasado"), Tabela_Movimentacao_Geral[[#This Row],[Status Financeiro]] ) -> Pendente | L28: =IF( $O$7="Desbloqueado", CHOOSE(RANDBETWEEN(1,3),"Entregue","Em Rota","Aguardando"), Tabela_Movimentacao_Geral[[#This Row],[Status Logistico]] ) -> Em Rota | M28: =IF( $O$7="Desbloqueado", IF( Tabela_Movimentacao_Geral[[#This Row],[Tipo Fluxo]]="Entrada", Tabela_Movimentacao_Geral[[#This Row],[Data]] + _xlfn.XLOOKUP(Tabela_Movimentacao_Geral[[#This Row],[ID Entidade]],Tabela_Fornecedores[ID_Fornecedor],Tabela_Fornecedores[Lead_Time]), "N/A" ), Tabela_Movimentacao_Geral[[#This Row],[Previsão de Entrega]] ) -> 45694
A29: ="T"&TEXT(ROW(A29)-1,"0000") -> T0028 | B29: 45679 | C29: {=IF($O$7="Desbloqueado", _xlfn.LET( _xlpm.saldo_atual, SUM(($C$2:$C28="Entrada")*($F$2:$F28=Tabela_Movimentacao_Geral[[#This Row],[ID Produto]])*($H$2:$H28) - ($C$2:$C28="Saida")*($F$2:$F28=Tabela_Movimentacao_Geral[[#This Row],[ID Produto]])*($H$2:$H28)), IF(_xlpm.saldo_atual > 0, IF(RANDBETWEEN(0,10)>3,"Saida","Entrada"), "Entrada") ), Tabela_Movimentacao_Geral[[#This Row],[Tipo Fluxo]] )} -> Entrada | D29: =IF( $O$7="Desbloqueado", IF( Tabela_Movimentacao_Geral[[#This Row],[Tipo Fluxo]]="Saida", "CLI"&TEXT(RANDBETWEEN(1,20),"000"), "FORN"&TEXT(RANDBETWEEN(1,20),"000") ), Tabela_Movimentacao_Geral[[#This Row],[ID Entidade]] ) -> FORN015 | E29: =IF(Tabela_Movimentacao_Geral[[#This Row],[Tipo Fluxo]]="Saida",_xlfn.XLOOKUP(Tabela_Movimentacao_Geral[[#This Row],[ID Entidade]], Tabela_Clientes[ID_Cliente],Tabela_Clientes[Nome_Cliente],"Cliente não encontrado"),_xlfn.XLOOKUP(Tabela_Movimentacao_Geral[[#This Row],[ID Entidade]], Tabela_Fornecedores[ID_Fornecedor], Tabela_Fornecedores[Nome_Fantasia], "Fornecedor não encontrado")) -> Print Smart | F29: =IF( $O$7="Desbloqueado", "PROD"&TEXT(RANDBETWEEN(1,200),"000"), Tabela_Movimentacao_Geral[[#This Row],[ID Produto]] ) -> PROD195 | G29: =_xlfn.XLOOKUP(Tabela_Movimentacao_Geral[[#This Row],[ID Produto]], Tabela_Produtos[ID_Produto],Tabela_Produtos[Descricao_Produto],"Produto não encontrado") -> Terminador Optico | H29: {=IF( $O$7="Desbloqueado", _xlfn.LET( _xlpm.saldo_atual, SUM(($C$2:$C28="Entrada")*($F$2:$F28=Tabela_Movimentacao_Geral[[#This Row],[ID Produto]])*($H$2:$H28) - ($C$2:$C28="Saida")*($F$2:$F28=Tabela_Movimentacao_Geral[[#This Row],[ID Produto]])*($H$2:$H28)), _xlpm.estoque_minimo, _xlfn.XLOOKUP(Tabela_Movimentacao_Geral[[#This Row],[ID Produto]], Tabela_Produtos[ID_Produto], Tabela_Produtos[Estoque_Minimo], 0), IF( _xlpm.saldo_atual > _xlpm.estoque_minimo, IF( Tabela_Movimentacao_Geral[[#This Row],[Tipo Fluxo]]="Saida", RANDBETWEEN(1, _xlpm.saldo_atual), RANDBETWEEN(1, 100) ), IF( Tabela_Movimentacao_Geral[[#This Row],[Tipo Fluxo]]="Saida", RANDBETWEEN(1, _xlpm.saldo_atual), IF( _xlpm.saldo_atual < 0, ABS(_xlpm.saldo_atual) + _xlpm.estoque_minimo + RANDBETWEEN(1, 100), _xlpm.estoque_minimo - _xlpm.saldo_atual + RANDBETWEEN(1, 100) ) ) ) ), Tabela_Movimentacao_Geral[[#This Row],[Quantidade]] )} -> 83 | I29: =_xlfn.XLOOKUP(Tabela_Movimentacao_Geral[[#This Row],[ID Produto]], Tabela_Produtos[ID_Produto],Tabela_Produtos[Preco_Unitario_Venda]) -> 120 | J29: =Tabela_Movimentacao_Geral[[#This Row],[Quantidade]] * Tabela_Movimentacao_Geral[[#This Row],[Valor Unitário]] -> 9960 | K29: =IF( $O$7="Desbloqueado", CHOOSE(RANDBETWEEN(1,3),"Pago","Pendente","Atrasado"), Tabela_Movimentacao_Geral[[#This Row],[Status Financeiro]] ) -> Pendente | L29: =IF( $O$7="Desbloqueado", CHOOSE(RANDBETWEEN(1,3),"Entregue","Em Rota","Aguardando"), Tabela_Movimentacao_Geral[[#This Row],[Status Logistico]] ) -> Aguardando | M29: =IF( $O$7="Desbloqueado", IF( Tabela_Movimentacao_Geral[[#This Row],[Tipo Fluxo]]="Entrada", Tabela_Movimentacao_Geral[[#This Row],[Data]] + _xlfn.XLOOKUP(Tabela_Movimentacao_Geral[[#This Row],[ID Entidade]],Tabela_Fornecedores[ID_Fornecedor],Tabela_Fornecedores[Lead_Time]), "N/A" ), Tabela_Movimentacao_Geral[[#This Row],[Previsão de Entrega]] ) -> 45682
A30: ="T"&TEXT(ROW(A30)-1,"0000") -> T0029 | B30: 45679 | C30: {=IF($O$7="Desbloqueado", _xlfn.LET( _xlpm.saldo_atual, SUM(($C$2:$C29="Entrada")*($F$2:$F29=Tabela_Movimentacao_Geral[[#This Row],[ID Produto]])*($H$2:$H29) - ($C$2:$C29="Saida")*($F$2:$F29=Tabela_Movimentacao_Geral[[#This Row],[ID Produto]])*($H$2:$H29)), IF(_xlpm.saldo_atual > 0, IF(RANDBETWEEN(0,10)>3,"Saida","Entrada"), "Entrada") ), Tabela_Movimentacao_Geral[[#This Row],[Tipo Fluxo]] )} -> Entrada | D30: =IF( $O$7="Desbloqueado", IF( Tabela_Movimentacao_Geral[[#This Row],[Tipo Fluxo]]="Saida", "CLI"&TEXT(RANDBETWEEN(1,20),"000"), "FORN"&TEXT(RANDBETWEEN(1,20),"000") ), Tabela_Movimentacao_Geral[[#This Row],[ID Entidade]] ) -> FORN001 | E30: =IF(Tabela_Movimentacao_Geral[[#This Row],[Tipo Fluxo]]="Saida",_xlfn.XLOOKUP(Tabela_Movimentacao_Geral[[#This Row],[ID Entidade]], Tabela_Clientes[ID_Cliente],Tabela_Clientes[Nome_Cliente],"Cliente não encontrado"),_xlfn.XLOOKUP(Tabela_Movimentacao_Geral[[#This Row],[ID Entidade]], Tabela_Fornecedores[ID_Fornecedor], Tabela_Fornecedores[Nome_Fantasia], "Fornecedor não encontrado")) -> TechFlow Solucoes | F30: =IF( $O$7="Desbloqueado", "PROD"&TEXT(RANDBETWEEN(1,200),"000"), Tabela_Movimentacao_Geral[[#This Row],[ID Produto]] ) -> PROD057 | G30: =_xlfn.XLOOKUP(Tabela_Movimentacao_Geral[[#This Row],[ID Produto]], Tabela_Produtos[ID_Produto],Tabela_Produtos[Descricao_Produto],"Produto não encontrado") -> Caneta Esferografica Azul | H30: {=IF( $O$7="Desbloqueado", _xlfn.LET( _xlpm.saldo_atual, SUM(($C$2:$C29="Entrada")*($F$2:$F29=Tabela_Movimentacao_Geral[[#This Row],[ID Produto]])*($H$2:$H29) - ($C$2:$C29="Saida")*($F$2:$F29=Tabela_Movimentacao_Geral[[#This Row],[ID Produto]])*($H$2:$H29)), _xlpm.estoque_minimo, _xlfn.XLOOKUP(Tabela_Movimentacao_Geral[[#This Row],[ID Produto]], Tabela_Produtos[ID_Produto], Tabela_Produtos[Estoque_Minimo], 0), IF( _xlpm.saldo_atual > _xlpm.estoque_minimo, IF( Tabela_Movimentacao_Geral[[#This Row],[Tipo Fluxo]]="Saida", RANDBETWEEN(1, _xlpm.saldo_atual), RANDBETWEEN(1, 100) ), IF( Tabela_Movimentacao_Geral[[#This Row],[Tipo Fluxo]]="Saida", RANDBETWEEN(1, _xlpm.saldo_atual), IF( _xlpm.saldo_atual < 0, ABS(_xlpm.saldo_atual) + _xlpm.estoque_minimo + RANDBETWEEN(1, 100), _xlpm.estoque_minimo - _xlpm.saldo_atual + RANDBETWEEN(1, 100) ) ) ) ), Tabela_Movimentacao_Geral[[#This Row],[Quantidade]] )} -> 574 | I30: =_xlfn.XLOOKUP(Tabela_Movimentacao_Geral[[#This Row],[ID Produto]], Tabela_Produtos[ID_Produto],Tabela_Produtos[Preco_Unitario_Venda]) -> 1.5 | J30: =Tabela_Movimentacao_Geral[[#This Row],[Quantidade]] * Tabela_Movimentacao_Geral[[#This Row],[Valor Unitário]] -> 861 | K30: =IF( $O$7="Desbloqueado", CHOOSE(RANDBETWEEN(1,3),"Pago","Pendente","Atrasado"), Tabela_Movimentacao_Geral[[#This Row],[Status Financeiro]] ) -> Pago | L30: =IF( $O$7="Desbloqueado", CHOOSE(RANDBETWEEN(1,3),"Entregue","Em Rota","Aguardando"), Tabela_Movimentacao_Geral[[#This Row],[Status Logistico]] ) -> Entregue | M30: =IF( $O$7="Desbloqueado", IF( Tabela_Movimentacao_Geral[[#This Row],[Tipo Fluxo]]="Entrada", Tabela_Movimentacao_Geral[[#This Row],[Data]] + _xlfn.XLOOKUP(Tabela_Movimentacao_Geral[[#This Row],[ID Entidade]],Tabela_Fornecedores[ID_Fornecedor],Tabela_Fornecedores[Lead_Time]), "N/A" ), Tabela_Movimentacao_Geral[[#This Row],[Previsão de Entrega]] ) -> 45684 | P30: =8 -> 8
A31: ="T"&TEXT(ROW(A31)-1,"0000") -> T0030 | B31: 45680 | C31: {=IF($O$7="Desbloqueado", _xlfn.LET( _xlpm.saldo_atual, SUM(($C$2:$C30="Entrada")*($F$2:$F30=Tabela_Movimentacao_Geral[[#This Row],[ID Produto]])*($H$2:$H30) - ($C$2:$C30="Saida")*($F$2:$F30=Tabela_Movimentacao_Geral[[#This Row],[ID Produto]])*($H$2:$H30)), IF(_xlpm.saldo_atual > 0, IF(RANDBETWEEN(0,10)>3,"Saida","Entrada"), "Entrada") ), Tabela_Movimentacao_Geral[[#This Row],[Tipo Fluxo]] )} -> Entrada | D31: =IF( $O$7="Desbloqueado", IF( Tabela_Movimentacao_Geral[[#This Row],[Tipo Fluxo]]="Saida", "CLI"&TEXT(RANDBETWEEN(1,20),"000"), "FORN"&TEXT(RANDBETWEEN(1,20),"000") ), Tabela_Movimentacao_Geral[[#This Row],[ID Entidade]] ) -> FORN015 | E31: =IF(Tabela_Movimentacao_Geral[[#This Row],[Tipo Fluxo]]="Saida",_xlfn.XLOOKUP(Tabela_Movimentacao_Geral[[#This Row],[ID Entidade]], Tabela_Clientes[ID_Cliente],Tabela_Clientes[Nome_Cliente],"Cliente não encontrado"),_xlfn.XLOOKUP(Tabela_Movimentacao_Geral[[#This Row],[ID Entidade]], Tabela_Fornecedores[ID_Fornecedor], Tabela_Fornecedores[Nome_Fantasia], "Fornecedor não encontrado")) -> Print Smart | F31: =IF( $O$7="Desbloqueado", "PROD"&TEXT(RANDBETWEEN(1,200),"000"), Tabela_Movimentacao_Geral[[#This Row],[ID Produto]] ) -> PROD078 | G31: =_xlfn.XLOOKUP(Tabela_Movimentacao_Geral[[#This Row],[ID Produto]], Tabela_Produtos[ID_Produto],Tabela_Produtos[Descricao_Produto],"Produto não encontrado") -> Porta Canetas Telado | H31: {=IF( $O$7="Desbloqueado", _xlfn.LET( _xlpm.saldo_atual, SUM(($C$2:$C30="Entrada")*($F$2:$F30=Tabela_Movimentacao_Geral[[#This Row],[ID Produto]])*($H$2:$H30) - ($C$2:$C30="Saida")*($F$2:$F30=Tabela_Movimentacao_Geral[[#This Row],[ID Produto]])*($H$2:$H30)), _xlpm.estoque_minimo, _xlfn.XLOOKUP(Tabela_Movimentacao_Geral[[#This Row],[ID Produto]], Tabela_Produtos[ID_Produto], Tabela_Produtos[Estoque_Minimo], 0), IF( _xlpm.saldo_atual > _xlpm.estoque_minimo, IF( Tabela_Movimentacao_Geral[[#This Row],[Tipo Fluxo]]="Saida", RANDBETWEEN(1, _xlpm.saldo_atual), RANDBETWEEN(1, 100) ), IF( Tabela_Movimentacao_Geral[[#This Row],[Tipo Fluxo]]="Saida", RANDBETWEEN(1, _xlpm.saldo_atual), IF( _xlpm.saldo_atual < 0, ABS(_xlpm.saldo_atual) + _xlpm.estoque_minimo + RANDBETWEEN(1, 100), _xlpm.estoque_minimo - _xlpm.saldo_atual + RANDBETWEEN(1, 100) ) ) ) ), Tabela_Movimentacao_Geral[[#This Row],[Quantidade]] )} -> 128 | I31: =_xlfn.XLOOKUP(Tabela_Movimentacao_Geral[[#This Row],[ID Produto]], Tabela_Produtos[ID_Produto],Tabela_Produtos[Preco_Unitario_Venda]) -> 15 | J31: =Tabela_Movimentacao_Geral[[#This Row],[Quantidade]] * Tabela_Movimentacao_Geral[[#This Row],[Valor Unitário]] -> 1920 | K31: =IF( $O$7="Desbloqueado", CHOOSE(RANDBETWEEN(1,3),"Pago","Pendente","Atrasado"), Tabela_Movimentacao_Geral[[#This Row],[Status Financeiro]] ) -> Pago | L31: =IF( $O$7="Desbloqueado", CHOOSE(RANDBETWEEN(1,3),"Entregue","Em Rota","Aguardando"), Tabela_Movimentacao_Geral[[#This Row],[Status Logistico]] ) -> Aguardando | M31: =IF( $O$7="Desbloqueado", IF( Tabela_Movimentacao_Geral[[#This Row],[Tipo Fluxo]]="Entrada", Tabela_Movimentacao_Geral[[#This Row],[Data]] + _xlfn.XLOOKUP(Tabela_Movimentacao_Geral[[#This Row],[ID Entidade]],Tabela_Fornecedores[ID_Fornecedor],Tabela_Fornecedores[Lead_Time]), "N/A" ), Tabela_Movimentacao_Geral[[#This Row],[Previsão de Entrega]] ) -> 45683
A32: ="T"&TEXT(ROW(A32)-1,"0000") -> T0031 | B32: 45680 | C32: {=IF($O$7="Desbloqueado", _xlfn.LET( _xlpm.saldo_atual, SUM(($C$2:$C31="Entrada")*($F$2:$F31=Tabela_Movimentacao_Geral[[#This Row],[ID Produto]])*($H$2:$H31) - ($C$2:$C31="Saida")*($F$2:$F31=Tabela_Movimentacao_Geral[[#This Row],[ID Produto]])*($H$2:$H31)), IF(_xlpm.saldo_atual > 0, IF(RANDBETWEEN(0,10)>3,"Saida","Entrada"), "Entrada") ), Tabela_Movimentacao_Geral[[#This Row],[Tipo Fluxo]] )} -> Entrada | D32: =IF( $O$7="Desbloqueado", IF( Tabela_Movimentacao_Geral[[#This Row],[Tipo Fluxo]]="Saida", "CLI"&TEXT(RANDBETWEEN(1,20),"000"), "FORN"&TEXT(RANDBETWEEN(1,20),"000") ), Tabela_Movimentacao_Geral[[#This Row],[ID Entidade]] ) -> FORN018 | E32: =IF(Tabela_Movimentacao_Geral[[#This Row],[Tipo Fluxo]]="Saida",_xlfn.XLOOKUP(Tabela_Movimentacao_Geral[[#This Row],[ID Entidade]], Tabela_Clientes[ID_Cliente],Tabela_Clientes[Nome_Cliente],"Cliente não encontrado"),_xlfn.XLOOKUP(Tabela_Movimentacao_Geral[[#This Row],[ID Entidade]], Tabela_Fornecedores[ID_Fornecedor], Tabela_Fornecedores[Nome_Fantasia], "Fornecedor não encontrado")) -> Link Direct | F32: =IF( $O$7="Desbloqueado", "PROD"&TEXT(RANDBETWEEN(1,200),"000"), Tabela_Movimentacao_Geral[[#This Row],[ID Produto]] ) -> PROD150 | G32: =_xlfn.XLOOKUP(Tabela_Movimentacao_Geral[[#This Row],[ID Produto]], Tabela_Produtos[ID_Produto],Tabela_Produtos[Descricao_Produto],"Produto não encontrado") -> Lanterna de Led Inspeção | H32: {=IF( $O$7="Desbloqueado", _xlfn.LET( _xlpm.saldo_atual, SUM(($C$2:$C31="Entrada")*($F$2:$F31=Tabela_Movimentacao_Geral[[#This Row],[ID Produto]])*($H$2:$H31) - ($C$2:$C31="Saida")*($F$2:$F31=Tabela_Movimentacao_Geral[[#This Row],[ID Produto]])*($H$2:$H31)), _xlpm.estoque_minimo, _xlfn.XLOOKUP(Tabela_Movimentacao_Geral[[#This Row],[ID Produto]], Tabela_Produtos[ID_Produto], Tabela_Produtos[Estoque_Minimo], 0), IF( _xlpm.saldo_atual > _xlpm.estoque_minimo, IF( Tabela_Movimentacao_Geral[[#This Row],[Tipo Fluxo]]="Saida", RANDBETWEEN(1, _xlpm.saldo_atual), RANDBETWEEN(1, 100) ), IF( Tabela_Movimentacao_Geral[[#This Row],[Tipo Fluxo]]="Saida", RANDBETWEEN(1, _xlpm.saldo_atual), IF( _xlpm.saldo_atual < 0, ABS(_xlpm.saldo_atual) + _xlpm.estoque_minimo + RANDBETWEEN(1, 100), _xlpm.estoque_minimo - _xlpm.saldo_atual + RANDBETWEEN(1, 100) ) ) ) ), Tabela_Movimentacao_Geral[[#This Row],[Quantidade]] )} -> 38 | I32: =_xlfn.XLOOKUP(Tabela_Movimentacao_Geral[[#This Row],[ID Produto]], Tabela_Produtos[ID_Produto],Tabela_Produtos[Preco_Unitario_Venda]) -> 55 | J32: =Tabela_Movimentacao_Geral[[#This Row],[Quantidade]] * Tabela_Movimentacao_Geral[[#This Row],[Valor Unitário]] -> 2090 | K32: =IF( $O$7="Desbloqueado", CHOOSE(RANDBETWEEN(1,3),"Pago","Pendente","Atrasado"), Tabela_Movimentacao_Geral[[#This Row],[Status Financeiro]] ) -> Atrasado | L32: =IF( $O$7="Desbloqueado", CHOOSE(RANDBETWEEN(1,3),"Entregue","Em Rota","Aguardando"), Tabela_Movimentacao_Geral[[#This Row],[Status Logistico]] ) -> Aguardando | M32: =IF( $O$7="Desbloqueado", IF( Tabela_Movimentacao_Geral[[#This Row],[Tipo Fluxo]]="Entrada", Tabela_Movimentacao_Geral[[#This Row],[Data]] + _xlfn.XLOOKUP(Tabela_Movimentacao_Geral[[#This Row],[ID Entidade]],Tabela_Fornecedores[ID_Fornecedor],Tabela_Fornecedores[Lead_Time]), "N/A" ), Tabela_Movimentacao_Geral[[#This Row],[Previsão de Entrega]] ) -> 45682
A33: ="T"&TEXT(ROW(A33)-1,"0000") -> T0032 | B33: 45680 | C33: {=IF($O$7="Desbloqueado", _xlfn.LET( _xlpm.saldo_atual, SUM(($C$2:$C32="Entrada")*($F$2:$F32=Tabela_Movimentacao_Geral[[#This Row],[ID Produto]])*($H$2:$H32) - ($C$2:$C32="Saida")*($F$2:$F32=Tabela_Movimentacao_Geral[[#This Row],[ID Produto]])*($H$2:$H32)), IF(_xlpm.saldo_atual > 0, IF(RANDBETWEEN(0,10)>3,"Saida","Entrada"), "Entrada") ), Tabela_Movimentacao_Geral[[#This Row],[Tipo Fluxo]] )} -> Entrada | D33: =IF( $O$7="Desbloqueado", IF( Tabela_Movimentacao_Geral[[#This Row],[Tipo Fluxo]]="Saida", "CLI"&TEXT(RANDBETWEEN(1,20),"000"), "FORN"&TEXT(RANDBETWEEN(1,20),"000") ), Tabela_Movimentacao_Geral[[#This Row],[ID Entidade]] ) -> FORN017 | E33: =IF(Tabela_Movimentacao_Geral[[#This Row],[Tipo Fluxo]]="Saida",_xlfn.XLOOKUP(Tabela_Movimentacao_Geral[[#This Row],[ID Entidade]], Tabela_Clientes[ID_Cliente],Tabela_Clientes[Nome_Cliente],"Cliente não encontrado"),_xlfn.XLOOKUP(Tabela_Movimentacao_Geral[[#This Row],[ID Entidade]], Tabela_Fornecedores[ID_Fornecedor], Tabela_Fornecedores[Nome_Fantasia], "Fornecedor não encontrado")) -> BitSafe | F33: =IF( $O$7="Desbloqueado", "PROD"&TEXT(RANDBETWEEN(1,200),"000"), Tabela_Movimentacao_Geral[[#This Row],[ID Produto]] ) -> PROD108 | G33: =_xlfn.XLOOKUP(Tabela_Movimentacao_Geral[[#This Row],[ID Produto]], Tabela_Produtos[ID_Produto],Tabela_Produtos[Descricao_Produto],"Produto não encontrado") -> Toner Colorido (Kit 4) | H33: {=IF( $O$7="Desbloqueado", _xlfn.LET( _xlpm.saldo_atual, SUM(($C$2:$C32="Entrada")*($F$2:$F32=Tabela_Movimentacao_Geral[[#This Row],[ID Produto]])*($H$2:$H32) - ($C$2:$C32="Saida")*($F$2:$F32=Tabela_Movimentacao_Geral[[#This Row],[ID Produto]])*($H$2:$H32)), _xlpm.estoque_minimo, _xlfn.XLOOKUP(Tabela_Movimentacao_Geral[[#This Row],[ID Produto]], Tabela_Produtos[ID_Produto], Tabela_Produtos[Estoque_Minimo], 0), IF( _xlpm.saldo_atual > _xlpm.estoque_minimo, IF( Tabela_Movimentacao_Geral[[#This Row],[Tipo Fluxo]]="Saida", RANDBETWEEN(1, _xlpm.saldo_atual), RANDBETWEEN(1, 100) ), IF( Tabela_Movimentacao_Geral[[#This Row],[Tipo Fluxo]]="Saida", RANDBETWEEN(1, _xlpm.saldo_atual), IF( _xlpm.saldo_atual < 0, ABS(_xlpm.saldo_atual) + _xlpm.estoque_minimo + RANDBETWEEN(1, 100), _xlpm.estoque_minimo - _xlpm.saldo_atual + RANDBETWEEN(1, 100) ) ) ) ), Tabela_Movimentacao_Geral[[#This Row],[Quantidade]] )} -> 35 | I33: =_xlfn.XLOOKUP(Tabela_Movimentacao_Geral[[#This Row],[ID Produto]], Tabela_Produtos[ID_Produto],Tabela_Produtos[Preco_Unitario_Venda]) -> 1200 | J33: =Tabela_Movimentacao_Geral[[#This Row],[Quantidade]] * Tabela_Movimentacao_Geral[[#This Row],[Valor Unitário]] -> 42000 | K33: =IF( $O$7="Desbloqueado", CHOOSE(RANDBETWEEN(1,3),"Pago","Pendente","Atrasado"), Tabela_Movimentacao_Geral[[#This Row],[Status Financeiro]] ) -> Atrasado | L33: =IF( $O$7="Desbloqueado", CHOOSE(RANDBETWEEN(1,3),"Entregue","Em Rota","Aguardando"), Tabela_Movimentacao_Geral[[#This Row],[Status Logistico]] ) -> Entregue | M33: =IF( $O$7="Desbloqueado", IF( Tabela_Movimentacao_Geral[[#This Row],[Tipo Fluxo]]="Entrada", Tabela_Movimentacao_Geral[[#This Row],[Data]] + _xlfn.XLOOKUP(Tabela_Movimentacao_Geral[[#This Row],[ID Entidade]],Tabela_Fornecedores[ID_Fornecedor],Tabela_Fornecedores[Lead_Time]), "N/A" ), Tabela_Movimentacao_Geral[[#This Row],[Previsão de Entrega]] ) -> 45683
A34: ="T"&TEXT(ROW(A34)-1,"0000") -> T0033 | B34: 45681 | C34: {=IF($O$7="Desbloqueado", _xlfn.LET( _xlpm.saldo_atual, SUM(($C$2:$C33="Entrada")*($F$2:$F33=Tabela_Movimentacao_Geral[[#This Row],[ID Produto]])*($H$2:$H33) - ($C$2:$C33="Saida")*($F$2:$F33=Tabela_Movimentacao_Geral[[#This Row],[ID Produto]])*($H$2:$H33)), IF(_xlpm.saldo_atual > 0, IF(RANDBETWEEN(0,10)>3,"Saida","Entrada"), "Entrada") ), Tabela_Movimentacao_Geral[[#This Row],[Tipo Fluxo]] )} -> Saida | D34: =IF( $O$7="Desbloqueado", IF( Tabela_Movimentacao_Geral[[#This Row],[Tipo Fluxo]]="Saida", "CLI"&TEXT(RANDBETWEEN(1,20),"000"), "FORN"&TEXT(RANDBETWEEN(1,20),"000") ), Tabela_Movimentacao_Geral[[#This Row],[ID Entidade]] ) -> CLI015 | E34: =IF(Tabela_Movimentacao_Geral[[#This Row],[Tipo Fluxo]]="Saida",_xlfn.XLOOKUP(Tabela_Movimentacao_Geral[[#This Row],[ID Entidade]], Tabela_Clientes[ID_Cliente],Tabela_Clientes[Nome_Cliente],"Cliente não encontrado"),_xlfn.XLOOKUP(Tabela_Movimentacao_Geral[[#This Row],[ID Entidade]], Tabela_Fornecedores[ID_Fornecedor], Tabela_Fornecedores[Nome_Fantasia], "Fornecedor não encontrado")) -> Pet Shop Amigo | F34: =IF( $O$7="Desbloqueado", "PROD"&TEXT(RANDBETWEEN(1,200),"000"), Tabela_Movimentacao_Geral[[#This Row],[ID Produto]] ) -> PROD128 | G34: =_xlfn.XLOOKUP(Tabela_Movimentacao_Geral[[#This Row],[ID Produto]], Tabela_Produtos[ID_Produto],Tabela_Produtos[Descricao_Produto],"Produto não encontrado") -> Cabo de Rede Cat5e 5m | H34: {=IF( $O$7="Desbloqueado", _xlfn.LET( _xlpm.saldo_atual, SUM(($C$2:$C33="Entrada")*($F$2:$F33=Tabela_Movimentacao_Geral[[#This Row],[ID Produto]])*($H$2:$H33) - ($C$2:$C33="Saida")*($F$2:$F33=Tabela_Movimentacao_Geral[[#This Row],[ID Produto]])*($H$2:$H33)), _xlpm.estoque_minimo, _xlfn.XLOOKUP(Tabela_Movimentacao_Geral[[#This Row],[ID Produto]], Tabela_Produtos[ID_Produto], Tabela_Produtos[Estoque_Minimo], 0), IF( _xlpm.saldo_atual > _xlpm.estoque_minimo, IF( Tabela_Movimentacao_Geral[[#This Row],[Tipo Fluxo]]="Saida", RANDBETWEEN(1, _xlpm.saldo_atual), RANDBETWEEN(1, 100) ), IF( Tabela_Movimentacao_Geral[[#This Row],[Tipo Fluxo]]="Saida", RANDBETWEEN(1, _xlpm.saldo_atual), IF( _xlpm.saldo_atual < 0, ABS(_xlpm.saldo_atual) + _xlpm.estoque_minimo + RANDBETWEEN(1, 100), _xlpm.estoque_minimo - _xlpm.saldo_atual + RANDBETWEEN(1, 100) ) ) ) ), Tabela_Movimentacao_Geral[[#This Row],[Quantidade]] )} -> 162 | I34: =_xlfn.XLOOKUP(Tabela_Movimentacao_Geral[[#This Row],[ID Produto]], Tabela_Produtos[ID_Produto],Tabela_Produtos[Preco_Unitario_Venda]) -> 18 | J34: =Tabela_Movimentacao_Geral[[#This Row],[Quantidade]] * Tabela_Movimentacao_Geral[[#This Row],[Valor Unitário]] -> 2916 | K34: =IF( $O$7="Desbloqueado", CHOOSE(RANDBETWEEN(1,3),"Pago","Pendente","Atrasado"), Tabela_Movimentacao_Geral[[#This Row],[Status Financeiro]] ) -> Pendente | L34: =IF( $O$7="Desbloqueado", CHOOSE(RANDBETWEEN(1,3),"Entregue","Em Rota","Aguardando"), Tabela_Movimentacao_Geral[[#This Row],[Status Logistico]] ) -> Em Rota | M34: =IF( $O$7="Desbloqueado", IF( Tabela_Movimentacao_Geral[[#This Row],[Tipo Fluxo]]="Entrada", Tabela_Movimentacao_Geral[[#This Row],[Data]] + _xlfn.XLOOKUP(Tabela_Movimentacao_Geral[[#This Row],[ID Entidade]],Tabela_Fornecedores[ID_Fornecedor],Tabela_Fornecedores[Lead_Time]), "N/A" ), Tabela_Movimentacao_Geral[[#This Row],[Previsão de Entrega]] ) -> N/A
A35: ="T"&TEXT(ROW(A35)-1,"0000") -> T0034 | B35: 45681 | C35: {=IF($O$7="Desbloqueado", _xlfn.LET( _xlpm.saldo_atual, SUM(($C$2:$C34="Entrada")*($F$2:$F34=Tabela_Movimentacao_Geral[[#This Row],[ID Produto]])*($H$2:$H34) - ($C$2:$C34="Saida")*($F$2:$F34=Tabela_Movimentacao_Geral[[#This Row],[ID Produto]])*($H$2:$H34)), IF(_xlpm.saldo_atual > 0, IF(RANDBETWEEN(0,10)>3,"Saida","Entrada"), "Entrada") ), Tabela_Movimentacao_Geral[[#This Row],[Tipo Fluxo]] )} -> Entrada | D35: =IF( $O$7="Desbloqueado", IF( Tabela_Movimentacao_Geral[[#This Row],[Tipo Fluxo]]="Saida", "CLI"&TEXT(RANDBETWEEN(1,20),"000"), "FORN"&TEXT(RANDBETWEEN(1,20),"000") ), Tabela_Movimentacao_Geral[[#This Row],[ID Entidade]] ) -> FORN003 | E35: =IF(Tabela_Movimentacao_Geral[[#This Row],[Tipo Fluxo]]="Saida",_xlfn.XLOOKUP(Tabela_Movimentacao_Geral[[#This Row],[ID Entidade]], Tabela_Clientes[ID_Cliente],Tabela_Clientes[Nome_Cliente],"Cliente não encontrado"),_xlfn.XLOOKUP(Tabela_Movimentacao_Geral[[#This Row],[ID Entidade]], Tabela_Fornecedores[ID_Fornecedor], Tabela_Fornecedores[Nome_Fantasia], "Fornecedor não encontrado")) -> Office Express | F35: =IF( $O$7="Desbloqueado", "PROD"&TEXT(RANDBETWEEN(1,200),"000"), Tabela_Movimentacao_Geral[[#This Row],[ID Produto]] ) -> PROD047 | G35: =_xlfn.XLOOKUP(Tabela_Movimentacao_Geral[[#This Row],[ID Produto]], Tabela_Produtos[ID_Produto],Tabela_Produtos[Descricao_Produto],"Produto não encontrado") -> Etiquetadora Termica | H35: {=IF( $O$7="Desbloqueado", _xlfn.LET( _xlpm.saldo_atual, SUM(($C$2:$C34="Entrada")*($F$2:$F34=Tabela_Movimentacao_Geral[[#This Row],[ID Produto]])*($H$2:$H34) - ($C$2:$C34="Saida")*($F$2:$F34=Tabela_Movimentacao_Geral[[#This Row],[ID Produto]])*($H$2:$H34)), _xlpm.estoque_minimo, _xlfn.XLOOKUP(Tabela_Movimentacao_Geral[[#This Row],[ID Produto]], Tabela_Produtos[ID_Produto], Tabela_Produtos[Estoque_Minimo], 0), IF( _xlpm.saldo_atual > _xlpm.estoque_minimo, IF( Tabela_Movimentacao_Geral[[#This Row],[Tipo Fluxo]]="Saida", RANDBETWEEN(1, _xlpm.saldo_atual), RANDBETWEEN(1, 100) ), IF( Tabela_Movimentacao_Geral[[#This Row],[Tipo Fluxo]]="Saida", RANDBETWEEN(1, _xlpm.saldo_atual), IF( _xlpm.saldo_atual < 0, ABS(_xlpm.saldo_atual) + _xlpm.estoque_minimo + RANDBETWEEN(1, 100), _xlpm.estoque_minimo - _xlpm.saldo_atual + RANDBETWEEN(1, 100) ) ) ) ), Tabela_Movimentacao_Geral[[#This Row],[Quantidade]] )} -> 32 | I35: =_xlfn.XLOOKUP(Tabela_Movimentacao_Geral[[#This Row],[ID Produto]], Tabela_Produtos[ID_Produto],Tabela_Produtos[Preco_Unitario_Venda]) -> 420 | J35: =Tabela_Movimentacao_Geral[[#This Row],[Quantidade]] * Tabela_Movimentacao_Geral[[#This Row],[Valor Unitário]] -> 13440 | K35: =IF( $O$7="Desbloqueado", CHOOSE(RANDBETWEEN(1,3),"Pago","Pendente","Atrasado"), Tabela_Movimentacao_Geral[[#This Row],[Status Financeiro]] ) -> Pago | L35: =IF( $O$7="Desbloqueado", CHOOSE(RANDBETWEEN(1,3),"Entregue","Em Rota","Aguardando"), Tabela_Movimentacao_Geral[[#This Row],[Status Logistico]] ) -> Em Rota | M35: =IF( $O$7="Desbloqueado", IF( Tabela_Movimentacao_Geral[[#This Row],[Tipo Fluxo]]="Entrada", Tabela_Movimentacao_Geral[[#This Row],[Data]] + _xlfn.XLOOKUP(Tabela_Movimentacao_Geral[[#This Row],[ID Entidade]],Tabela_Fornecedores[ID_Fornecedor],Tabela_Fornecedores[Lead_Time]), "N/A" ), Tabela_Movimentacao_Geral[[#This Row],[Previsão de Entrega]] ) -> 45683
A36: ="T"&TEXT(ROW(A36)-1,"0000") -> T0035 | B36: 45681 | C36: {=IF($O$7="Desbloqueado", _xlfn.LET( _xlpm.saldo_atual, SUM(($C$2:$C35="Entrada")*($F$2:$F35=Tabela_Movimentacao_Geral[[#This Row],[ID Produto]])*($H$2:$H35) - ($C$2:$C35="Saida")*($F$2:$F35=Tabela_Movimentacao_Geral[[#This Row],[ID Produto]])*($H$2:$H35)), IF(_xlpm.saldo_atual > 0, IF(RANDBETWEEN(0,10)>3,"Saida","Entrada"), "Entrada") ), Tabela_Movimentacao_Geral[[#This Row],[Tipo Fluxo]] )} -> Entrada | D36: =IF( $O$7="Desbloqueado", IF( Tabela_Movimentacao_Geral[[#This Row],[Tipo Fluxo]]="Saida", "CLI"&TEXT(RANDBETWEEN(1,20),"000"), "FORN"&TEXT(RANDBETWEEN(1,20),"000") ), Tabela_Movimentacao_Geral[[#This Row],[ID Entidade]] ) -> FORN007 | E36: =IF(Tabela_Movimentacao_Geral[[#This Row],[Tipo Fluxo]]="Saida",_xlfn.XLOOKUP(Tabela_Movimentacao_Geral[[#This Row],[ID Entidade]], Tabela_Clientes[ID_Cliente],Tabela_Clientes[Nome_Cliente],"Cliente não encontrado"),_xlfn.XLOOKUP(Tabela_Movimentacao_Geral[[#This Row],[ID Entidade]], Tabela_Fornecedores[ID_Fornecedor], Tabela_Fornecedores[Nome_Fantasia], "Fornecedor não encontrado")) -> CyberSecurity SA | F36: =IF( $O$7="Desbloqueado", "PROD"&TEXT(RANDBETWEEN(1,200),"000"), Tabela_Movimentacao_Geral[[#This Row],[ID Produto]] ) -> PROD090 | G36: =_xlfn.XLOOKUP(Tabela_Movimentacao_Geral[[#This Row],[ID Produto]], Tabela_Produtos[ID_Produto],Tabela_Produtos[Descricao_Produto],"Produto não encontrado") -> Bandeja Fixa para Rack | H36: {=IF( $O$7="Desbloqueado", _xlfn.LET( _xlpm.saldo_atual, SUM(($C$2:$C35="Entrada")*($F$2:$F35=Tabela_Movimentacao_Geral[[#This Row],[ID Produto]])*($H$2:$H35) - ($C$2:$C35="Saida")*($F$2:$F35=Tabela_Movimentacao_Geral[[#This Row],[ID Produto]])*($H$2:$H35)), _xlpm.estoque_minimo, _xlfn.XLOOKUP(Tabela_Movimentacao_Geral[[#This Row],[ID Produto]], Tabela_Produtos[ID_Produto], Tabela_Produtos[Estoque_Minimo], 0), IF( _xlpm.saldo_atual > _xlpm.estoque_minimo, IF( Tabela_Movimentacao_Geral[[#This Row],[Tipo Fluxo]]="Saida", RANDBETWEEN(1, _xlpm.saldo_atual), RANDBETWEEN(1, 100) ), IF( Tabela_Movimentacao_Geral[[#This Row],[Tipo Fluxo]]="Saida", RANDBETWEEN(1, _xlpm.saldo_atual), IF( _xlpm.saldo_atual < 0, ABS(_xlpm.saldo_atual) + _xlpm.estoque_minimo + RANDBETWEEN(1, 100), _xlpm.estoque_minimo - _xlpm.saldo_atual + RANDBETWEEN(1, 100) ) ) ) ), Tabela_Movimentacao_Geral[[#This Row],[Quantidade]] )} -> 78 | I36: =_xlfn.XLOOKUP(Tabela_Movimentacao_Geral[[#This Row],[ID Produto]], Tabela_Produtos[ID_Produto],Tabela_Produtos[Preco_Unitario_Venda]) -> 140 | J36: =Tabela_Movimentacao_Geral[[#This Row],[Quantidade]] * Tabela_Movimentacao_Geral[[#This Row],[Valor Unitário]] -> 10920 | K36: =IF( $O$7="Desbloqueado", CHOOSE(RANDBETWEEN(1,3),"Pago","Pendente","Atrasado"), Tabela_Movimentacao_Geral[[#This Row],[Status Financeiro]] ) -> Pago | L36: =IF( $O$7="Desbloqueado", CHOOSE(RANDBETWEEN(1,3),"Entregue","Em Rota","Aguardando"), Tabela_Movimentacao_Geral[[#This Row],[Status Logistico]] ) -> Entregue | M36: =IF( $O$7="Desbloqueado", IF( Tabela_Movimentacao_Geral[[#This Row],[Tipo Fluxo]]="Entrada", Tabela_Movimentacao_Geral[[#This Row],[Data]] + _xlfn.XLOOKUP(Tabela_Movimentacao_Geral[[#This Row],[ID Entidade]],Tabela_Fornecedores[ID_Fornecedor],Tabela_Fornecedores[Lead_Time]), "N/A" ), Tabela_Movimentacao_Geral[[#This Row],[Previsão de Entrega]] ) -> 45688
A37: ="T"&TEXT(ROW(A37)-1,"0000") -> T0036 | B37: 45681 | C37: {=IF($O$7="Desbloqueado", _xlfn.LET( _xlpm.saldo_atual, SUM(($C$2:$C36="Entrada")*($F$2:$F36=Tabela_Movimentacao_Geral[[#This Row],[ID Produto]])*($H$2:$H36) - ($C$2:$C36="Saida")*($F$2:$F36=Tabela_Movimentacao_Geral[[#This Row],[ID Produto]])*($H$2:$H36)), IF(_xlpm.saldo_atual > 0, IF(RANDBETWEEN(0,10)>3,"Saida","Entrada"), "Entrada") ), Tabela_Movimentacao_Geral[[#This Row],[Tipo Fluxo]] )} -> Entrada | D37: =IF( $O$7="Desbloqueado", IF( Tabela_Movimentacao_Geral[[#This Row],[Tipo Fluxo]]="Saida", "CLI"&TEXT(RANDBETWEEN(1,20),"000"), "FORN"&TEXT(RANDBETWEEN(1,20),"000") ), Tabela_Movimentacao_Geral[[#This Row],[ID Entidade]] ) -> FORN001 | E37: =IF(Tabela_Movimentacao_Geral[[#This Row],[Tipo Fluxo]]="Saida",_xlfn.XLOOKUP(Tabela_Movimentacao_Geral[[#This Row],[ID Entidade]], Tabela_Clientes[ID_Cliente],Tabela_Clientes[Nome_Cliente],"Cliente não encontrado"),_xlfn.XLOOKUP(Tabela_Movimentacao_Geral[[#This Row],[ID Entidade]], Tabela_Fornecedores[ID_Fornecedor], Tabela_Fornecedores[Nome_Fantasia], "Fornecedor não encontrado")) -> TechFlow Solucoes | F37: =IF( $O$7="Desbloqueado", "PROD"&TEXT(RANDBETWEEN(1,200),"000"), Tabela_Movimentacao_Geral[[#This Row],[ID Produto]] ) -> PROD070 | G37: =_xlfn.XLOOKUP(Tabela_Movimentacao_Geral[[#This Row],[ID Produto]], Tabela_Produtos[ID_Produto],Tabela_Produtos[Descricao_Produto],"Produto não encontrado") -> Marcador para Quadro Azul | H37: {=IF( $O$7="Desbloqueado", _xlfn.LET( _xlpm.saldo_atual, SUM(($C$2:$C36="Entrada")*($F$2:$F36=Tabela_Movimentacao_Geral[[#This Row],[ID Produto]])*($H$2:$H36) - ($C$2:$C36="Saida")*($F$2:$F36=Tabela_Movimentacao_Geral[[#This Row],[ID Produto]])*($H$2:$H36)), _xlpm.estoque_minimo, _xlfn.XLOOKUP(Tabela_Movimentacao_Geral[[#This Row],[ID Produto]], Tabela_Produtos[ID_Produto], Tabela_Produtos[Estoque_Minimo], 0), IF( _xlpm.saldo_atual > _xlpm.estoque_minimo, IF( Tabela_Movimentacao_Geral[[#This Row],[Tipo Fluxo]]="Saida", RANDBETWEEN(1, _xlpm.saldo_atual), RANDBETWEEN(1, 100) ), IF( Tabela_Movimentacao_Geral[[#This Row],[Tipo Fluxo]]="Saida", RANDBETWEEN(1, _xlpm.saldo_atual), IF( _xlpm.saldo_atual < 0, ABS(_xlpm.saldo_atual) + _xlpm.estoque_minimo + RANDBETWEEN(1, 100), _xlpm.estoque_minimo - _xlpm.saldo_atual + RANDBETWEEN(1, 100) ) ) ) ), Tabela_Movimentacao_Geral[[#This Row],[Quantidade]] )} -> 168 | I37: =_xlfn.XLOOKUP(Tabela_Movimentacao_Geral[[#This Row],[ID Produto]], Tabela_Produtos[ID_Produto],Tabela_Produtos[Preco_Unitario_Venda]) -> 7.5 | J37: =Tabela_Movimentacao_Geral[[#This Row],[Quantidade]] * Tabela_Movimentacao_Geral[[#This Row],[Valor Unitário]] -> 1260 | K37: =IF( $O$7="Desbloqueado", CHOOSE(RANDBETWEEN(1,3),"Pago","Pendente","Atrasado"), Tabela_Movimentacao_Geral[[#This Row],[Status Financeiro]] ) -> Pendente | L37: =IF( $O$7="Desbloqueado", CHOOSE(RANDBETWEEN(1,3),"Entregue","Em Rota","Aguardando"), Tabela_Movimentacao_Geral[[#This Row],[Status Logistico]] ) -> Entregue | M37: =IF( $O$7="Desbloqueado", IF( Tabela_Movimentacao_Geral[[#This Row],[Tipo Fluxo]]="Entrada", Tabela_Movimentacao_Geral[[#This Row],[Data]] + _xlfn.XLOOKUP(Tabela_Movimentacao_Geral[[#This Row],[ID Entidade]],Tabela_Fornecedores[ID_Fornecedor],Tabela_Fornecedores[Lead_Time]), "N/A" ), Tabela_Movimentacao_Geral[[#This Row],[Previsão de Entrega]] ) -> 45686
A38: ="T"&TEXT(ROW(A38)-1,"0000") -> T0037 | B38: 45682 | C38: {=IF($O$7="Desbloqueado", _xlfn.LET( _xlpm.saldo_atual, SUM(($C$2:$C37="Entrada")*($F$2:$F37=Tabela_Movimentacao_Geral[[#This Row],[ID Produto]])*($H$2:$H37) - ($C$2:$C37="Saida")*($F$2:$F37=Tabela_Movimentacao_Geral[[#This Row],[ID Produto]])*($H$2:$H37)), IF(_xlpm.saldo_atual > 0, IF(RANDBETWEEN(0,10)>3,"Saida","Entrada"), "Entrada") ), Tabela_Movimentacao_Geral[[#This Row],[Tipo Fluxo]] )} -> Entrada | D38: =IF( $O$7="Desbloqueado", IF( Tabela_Movimentacao_Geral[[#This Row],[Tipo Fluxo]]="Saida", "CLI"&TEXT(RANDBETWEEN(1,20),"000"), "FORN"&TEXT(RANDBETWEEN(1,20),"000") ), Tabela_Movimentacao_Geral[[#This Row],[ID Entidade]] ) -> FORN014 | E38: =IF(Tabela_Movimentacao_Geral[[#This Row],[Tipo Fluxo]]="Saida",_xlfn.XLOOKUP(Tabela_Movimentacao_Geral[[#This Row],[ID Entidade]], Tabela_Clientes[ID_Cliente],Tabela_Clientes[Nome_Cliente],"Cliente não encontrado"),_xlfn.XLOOKUP(Tabela_Movimentacao_Geral[[#This Row],[ID Entidade]], Tabela_Fornecedores[ID_Fornecedor], Tabela_Fornecedores[Nome_Fantasia], "Fornecedor não encontrado")) -> DevTools Inc | F38: =IF( $O$7="Desbloqueado", "PROD"&TEXT(RANDBETWEEN(1,200),"000"), Tabela_Movimentacao_Geral[[#This Row],[ID Produto]] ) -> PROD058 | G38: =_xlfn.XLOOKUP(Tabela_Movimentacao_Geral[[#This Row],[ID Produto]], Tabela_Produtos[ID_Produto],Tabela_Produtos[Descricao_Produto],"Produto não encontrado") -> Caneta Esferografica Preta | H38: {=IF( $O$7="Desbloqueado", _xlfn.LET( _xlpm.saldo_atual, SUM(($C$2:$C37="Entrada")*($F$2:$F37=Tabela_Movimentacao_Geral[[#This Row],[ID Produto]])*($H$2:$H37) - ($C$2:$C37="Saida")*($F$2:$F37=Tabela_Movimentacao_Geral[[#This Row],[ID Produto]])*($H$2:$H37)), _xlpm.estoque_minimo, _xlfn.XLOOKUP(Tabela_Movimentacao_Geral[[#This Row],[ID Produto]], Tabela_Produtos[ID_Produto], Tabela_Produtos[Estoque_Minimo], 0), IF( _xlpm.saldo_atual > _xlpm.estoque_minimo, IF( Tabela_Movimentacao_Geral[[#This Row],[Tipo Fluxo]]="Saida", RANDBETWEEN(1, _xlpm.saldo_atual), RANDBETWEEN(1, 100) ), IF( Tabela_Movimentacao_Geral[[#This Row],[Tipo Fluxo]]="Saida", RANDBETWEEN(1, _xlpm.saldo_atual), IF( _xlpm.saldo_atual < 0, ABS(_xlpm.saldo_atual) + _xlpm.estoque_minimo + RANDBETWEEN(1, 100), _xlpm.estoque_minimo - _xlpm.saldo_atual + RANDBETWEEN(1, 100) ) ) ) ), Tabela_Movimentacao_Geral[[#This Row],[Quantidade]] )} -> 540 | I38: =_xlfn.XLOOKUP(Tabela_Movimentacao_Geral[[#This Row],[ID Produto]], Tabela_Produtos[ID_Produto],Tabela_Produtos[Preco_Unitario_Venda]) -> 1.5 | J38: =Tabela_Movimentacao_Geral[[#This Row],[Quantidade]] * Tabela_Movimentacao_Geral[[#This Row],[Valor Unitário]] -> 810 | K38: =IF( $O$7="Desbloqueado", CHOOSE(RANDBETWEEN(1,3),"Pago","Pendente","Atrasado"), Tabela_Movimentacao_Geral[[#This Row],[Status Financeiro]] ) -> Atrasado | L38: =IF( $O$7="Desbloqueado", CHOOSE(RANDBETWEEN(1,3),"Entregue","Em Rota","Aguardando"), Tabela_Movimentacao_Geral[[#This Row],[Status Logistico]] ) -> Em Rota | M38: =IF( $O$7="Desbloqueado", IF( Tabela_Movimentacao_Geral[[#This Row],[Tipo Fluxo]]="Entrada", Tabela_Movimentacao_Geral[[#This Row],[Data]] + _xlfn.XLOOKUP(Tabela_Movimentacao_Geral[[#This Row],[ID Entidade]],Tabela_Fornecedores[ID_Fornecedor],Tabela_Fornecedores[Lead_Time]), "N/A" ), Tabela_Movimentacao_Geral[[#This Row],[Previsão de Entrega]] ) -> 45683
A39: ="T"&TEXT(ROW(A39)-1,"0000") -> T0038 | B39: 45682 | C39: {=IF($O$7="Desbloqueado", _xlfn.LET( _xlpm.saldo_atual, SUM(($C$2:$C38="Entrada")*($F$2:$F38=Tabela_Movimentacao_Geral[[#This Row],[ID Produto]])*($H$2:$H38) - ($C$2:$C38="Saida")*($F$2:$F38=Tabela_Movimentacao_Geral[[#This Row],[ID Produto]])*($H$2:$H38)), IF(_xlpm.saldo_atual > 0, IF(RANDBETWEEN(0,10)>3,"Saida","Entrada"), "Entrada") ), Tabela_Movimentacao_Geral[[#This Row],[Tipo Fluxo]] )} -> Saida | D39: =IF( $O$7="Desbloqueado", IF( Tabela_Movimentacao_Geral[[#This Row],[Tipo Fluxo]]="Saida", "CLI"&TEXT(RANDBETWEEN(1,20),"000"), "FORN"&TEXT(RANDBETWEEN(1,20),"000") ), Tabela_Movimentacao_Geral[[#This Row],[ID Entidade]] ) -> CLI016 | E39: =IF(Tabela_Movimentacao_Geral[[#This Row],[Tipo Fluxo]]="Saida",_xlfn.XLOOKUP(Tabela_Movimentacao_Geral[[#This Row],[ID Entidade]], Tabela_Clientes[ID_Cliente],Tabela_Clientes[Nome_Cliente],"Cliente não encontrado"),_xlfn.XLOOKUP(Tabela_Movimentacao_Geral[[#This Row],[ID Entidade]], Tabela_Fornecedores[ID_Fornecedor], Tabela_Fornecedores[Nome_Fantasia], "Fornecedor não encontrado")) -> Auto Pecas Jato | F39: =IF( $O$7="Desbloqueado", "PROD"&TEXT(RANDBETWEEN(1,200),"000"), Tabela_Movimentacao_Geral[[#This Row],[ID Produto]] ) -> PROD175 | G39: =_xlfn.XLOOKUP(Tabela_Movimentacao_Geral[[#This Row],[ID Produto]], Tabela_Produtos[ID_Produto],Tabela_Produtos[Descricao_Produto],"Produto não encontrado") -> Plastico Bolha 1.2x50m | H39: {=IF( $O$7="Desbloqueado", _xlfn.LET( _xlpm.saldo_atual, SUM(($C$2:$C38="Entrada")*($F$2:$F38=Tabela_Movimentacao_Geral[[#This Row],[ID Produto]])*($H$2:$H38) - ($C$2:$C38="Saida")*($F$2:$F38=Tabela_Movimentacao_Geral[[#This Row],[ID Produto]])*($H$2:$H38)), _xlpm.estoque_minimo, _xlfn.XLOOKUP(Tabela_Movimentacao_Geral[[#This Row],[ID Produto]], Tabela_Produtos[ID_Produto], Tabela_Produtos[Estoque_Minimo], 0), IF( _xlpm.saldo_atual > _xlpm.estoque_minimo, IF( Tabela_Movimentacao_Geral[[#This Row],[Tipo Fluxo]]="Saida", RANDBETWEEN(1, _xlpm.saldo_atual), RANDBETWEEN(1, 100) ), IF( Tabela_Movimentacao_Geral[[#This Row],[Tipo Fluxo]]="Saida", RANDBETWEEN(1, _xlpm.saldo_atual), IF( _xlpm.saldo_atual < 0, ABS(_xlpm.saldo_atual) + _xlpm.estoque_minimo + RANDBETWEEN(1, 100), _xlpm.estoque_minimo - _xlpm.saldo_atual + RANDBETWEEN(1, 100) ) ) ) ), Tabela_Movimentacao_Geral[[#This Row],[Quantidade]] )} -> 69 | I39: =_xlfn.XLOOKUP(Tabela_Movimentacao_Geral[[#This Row],[ID Produto]], Tabela_Produtos[ID_Produto],Tabela_Produtos[Preco_Unitario_Venda]) -> 110 | J39: =Tabela_Movimentacao_Geral[[#This Row],[Quantidade]] * Tabela_Movimentacao_Geral[[#This Row],[Valor Unitário]] -> 7590 | K39: =IF( $O$7="Desbloqueado", CHOOSE(RANDBETWEEN(1,3),"Pago","Pendente","Atrasado"), Tabela_Movimentacao_Geral[[#This Row],[Status Financeiro]] ) -> Pendente | L39: =IF( $O$7="Desbloqueado", CHOOSE(RANDBETWEEN(1,3),"Entregue","Em Rota","Aguardando"), Tabela_Movimentacao_Geral[[#This Row],[Status Logistico]] ) -> Aguardando | M39: =IF( $O$7="Desbloqueado", IF( Tabela_Movimentacao_Geral[[#This Row],[Tipo Fluxo]]="Entrada", Tabela_Movimentacao_Geral[[#This Row],[Data]] + _xlfn.XLOOKUP(Tabela_Movimentacao_Geral[[#This Row],[ID Entidade]],Tabela_Fornecedores[ID_Fornecedor],Tabela_Fornecedores[Lead_Time]), "N/A" ), Tabela_Movimentacao_Geral[[#This Row],[Previsão de Entrega]] ) -> N/A
A40: ="T"&TEXT(ROW(A40)-1,"0000") -> T0039 | B40: 45682 | C40: {=IF($O$7="Desbloqueado", _xlfn.LET( _xlpm.saldo_atual, SUM(($C$2:$C39="Entrada")*($F$2:$F39=Tabela_Movimentacao_Geral[[#This Row],[ID Produto]])*($H$2:$H39) - ($C$2:$C39="Saida")*($F$2:$F39=Tabela_Movimentacao_Geral[[#This Row],[ID Produto]])*($H$2:$H39)), IF(_xlpm.saldo_atual > 0, IF(RANDBETWEEN(0,10)>3,"Saida","Entrada"), "Entrada") ), Tabela_Movimentacao_Geral[[#This Row],[Tipo Fluxo]] )} -> Entrada | D40: =IF( $O$7="Desbloqueado", IF( Tabela_Movimentacao_Geral[[#This Row],[Tipo Fluxo]]="Saida", "CLI"&TEXT(RANDBETWEEN(1,20),"000"), "FORN"&TEXT(RANDBETWEEN(1,20),"000") ), Tabela_Movimentacao_Geral[[#This Row],[ID Entidade]] ) -> FORN012 | E40: =IF(Tabela_Movimentacao_Geral[[#This Row],[Tipo Fluxo]]="Saida",_xlfn.XLOOKUP(Tabela_Movimentacao_Geral[[#This Row],[ID Entidade]], Tabela_Clientes[ID_Cliente],Tabela_Clientes[Nome_Cliente],"Cliente não encontrado"),_xlfn.XLOOKUP(Tabela_Movimentacao_Geral[[#This Row],[ID Entidade]], Tabela_Fornecedores[ID_Fornecedor], Tabela_Fornecedores[Nome_Fantasia], "Fornecedor não encontrado")) -> Fast Delivery | F40: =IF( $O$7="Desbloqueado", "PROD"&TEXT(RANDBETWEEN(1,200),"000"), Tabela_Movimentacao_Geral[[#This Row],[ID Produto]] ) -> PROD185 | G40: =_xlfn.XLOOKUP(Tabela_Movimentacao_Geral[[#This Row],[ID Produto]], Tabela_Produtos[ID_Produto],Tabela_Produtos[Descricao_Produto],"Produto não encontrado") -> PDU Básica 12 Tomadas | H40: {=IF( $O$7="Desbloqueado", _xlfn.LET( _xlpm.saldo_atual, SUM(($C$2:$C39="Entrada")*($F$2:$F39=Tabela_Movimentacao_Geral[[#This Row],[ID Produto]])*($H$2:$H39) - ($C$2:$C39="Saida")*($F$2:$F39=Tabela_Movimentacao_Geral[[#This Row],[ID Produto]])*($H$2:$H39)), _xlpm.estoque_minimo, _xlfn.XLOOKUP(Tabela_Movimentacao_Geral[[#This Row],[ID Produto]], Tabela_Produtos[ID_Produto], Tabela_Produtos[Estoque_Minimo], 0), IF( _xlpm.saldo_atual > _xlpm.estoque_minimo, IF( Tabela_Movimentacao_Geral[[#This Row],[Tipo Fluxo]]="Saida", RANDBETWEEN(1, _xlpm.saldo_atual), RANDBETWEEN(1, 100) ), IF( Tabela_Movimentacao_Geral[[#This Row],[Tipo Fluxo]]="Saida", RANDBETWEEN(1, _xlpm.saldo_atual), IF( _xlpm.saldo_atual < 0, ABS(_xlpm.saldo_atual) + _xlpm.estoque_minimo + RANDBETWEEN(1, 100), _xlpm.estoque_minimo - _xlpm.saldo_atual + RANDBETWEEN(1, 100) ) ) ) ), Tabela_Movimentacao_Geral[[#This Row],[Quantidade]] )} -> 59 | I40: =_xlfn.XLOOKUP(Tabela_Movimentacao_Geral[[#This Row],[ID Produto]], Tabela_Produtos[ID_Produto],Tabela_Produtos[Preco_Unitario_Venda]) -> 380 | J40: =Tabela_Movimentacao_Geral[[#This Row],[Quantidade]] * Tabela_Movimentacao_Geral[[#This Row],[Valor Unitário]] -> 22420 | K40: =IF( $O$7="Desbloqueado", CHOOSE(RANDBETWEEN(1,3),"Pago","Pendente","Atrasado"), Tabela_Movimentacao_Geral[[#This Row],[Status Financeiro]] ) -> Pago | L40: =IF( $O$7="Desbloqueado", CHOOSE(RANDBETWEEN(1,3),"Entregue","Em Rota","Aguardando"), Tabela_Movimentacao_Geral[[#This Row],[Status Logistico]] ) -> Aguardando | M40: =IF( $O$7="Desbloqueado", IF( Tabela_Movimentacao_Geral[[#This Row],[Tipo Fluxo]]="Entrada", Tabela_Movimentacao_Geral[[#This Row],[Data]] + _xlfn.XLOOKUP(Tabela_Movimentacao_Geral[[#This Row],[ID Entidade]],Tabela_Fornecedores[ID_Fornecedor],Tabela_Fornecedores[Lead_Time]), "N/A" ), Tabela_Movimentacao_Geral[[#This Row],[Previsão de Entrega]] ) -> 45683
A41: ="T"&TEXT(ROW(A41)-1,"0000") -> T0040 | B41: 45682 | C41: {=IF($O$7="Desbloqueado", _xlfn.LET( _xlpm.saldo_atual, SUM(($C$2:$C40="Entrada")*($F$2:$F40=Tabela_Movimentacao_Geral[[#This Row],[ID Produto]])*($H$2:$H40) - ($C$2:$C40="Saida")*($F$2:$F40=Tabela_Movimentacao_Geral[[#This Row],[ID Produto]])*($H$2:$H40)), IF(_xlpm.saldo_atual > 0, IF(RANDBETWEEN(0,10)>3,"Saida","Entrada"), "Entrada") ), Tabela_Movimentacao_Geral[[#This Row],[Tipo Fluxo]] )} -> Entrada | D41: =IF( $O$7="Desbloqueado", IF( Tabela_Movimentacao_Geral[[#This Row],[Tipo Fluxo]]="Saida", "CLI"&TEXT(RANDBETWEEN(1,20),"000"), "FORN"&TEXT(RANDBETWEEN(1,20),"000") ), Tabela_Movimentacao_Geral[[#This Row],[ID Entidade]] ) -> FORN011 | E41: =IF(Tabela_Movimentacao_Geral[[#This Row],[Tipo Fluxo]]="Saida",_xlfn.XLOOKUP(Tabela_Movimentacao_Geral[[#This Row],[ID Entidade]], Tabela_Clientes[ID_Cliente],Tabela_Clientes[Nome_Cliente],"Cliente não encontrado"),_xlfn.XLOOKUP(Tabela_Movimentacao_Geral[[#This Row],[ID Entidade]], Tabela_Fornecedores[ID_Fornecedor], Tabela_Fornecedores[Nome_Fantasia], "Fornecedor não encontrado")) -> Energy Solution | F41: =IF( $O$7="Desbloqueado", "PROD"&TEXT(RANDBETWEEN(1,200),"000"), Tabela_Movimentacao_Geral[[#This Row],[ID Produto]] ) -> PROD052 | G41: =_xlfn.XLOOKUP(Tabela_Movimentacao_Geral[[#This Row],[ID Produto]], Tabela_Produtos[ID_Produto],Tabela_Produtos[Descricao_Produto],"Produto não encontrado") -> Clips Metalicos 33mm 100un | H41: {=IF( $O$7="Desbloqueado", _xlfn.LET( _xlpm.saldo_atual, SUM(($C$2:$C40="Entrada")*($F$2:$F40=Tabela_Movimentacao_Geral[[#This Row],[ID Produto]])*($H$2:$H40) - ($C$2:$C40="Saida")*($F$2:$F40=Tabela_Movimentacao_Geral[[#This Row],[ID Produto]])*($H$2:$H40)), _xlpm.estoque_minimo, _xlfn.XLOOKUP(Tabela_Movimentacao_Geral[[#This Row],[ID Produto]], Tabela_Produtos[ID_Produto], Tabela_Produtos[Estoque_Minimo], 0), IF( _xlpm.saldo_atual > _xlpm.estoque_minimo, IF( Tabela_Movimentacao_Geral[[#This Row],[Tipo Fluxo]]="Saida", RANDBETWEEN(1, _xlpm.saldo_atual), RANDBETWEEN(1, 100) ), IF( Tabela_Movimentacao_Geral[[#This Row],[Tipo Fluxo]]="Saida", RANDBETWEEN(1, _xlpm.saldo_atual), IF( _xlpm.saldo_atual < 0, ABS(_xlpm.saldo_atual) + _xlpm.estoque_minimo + RANDBETWEEN(1, 100), _xlpm.estoque_minimo - _xlpm.saldo_atual + RANDBETWEEN(1, 100) ) ) ) ), Tabela_Movimentacao_Geral[[#This Row],[Quantidade]] )} -> 256 | I41: =_xlfn.XLOOKUP(Tabela_Movimentacao_Geral[[#This Row],[ID Produto]], Tabela_Produtos[ID_Produto],Tabela_Produtos[Preco_Unitario_Venda]) -> 6.5 | J41: =Tabela_Movimentacao_Geral[[#This Row],[Quantidade]] * Tabela_Movimentacao_Geral[[#This Row],[Valor Unitário]] -> 1664 | K41: =IF( $O$7="Desbloqueado", CHOOSE(RANDBETWEEN(1,3),"Pago","Pendente","Atrasado"), Tabela_Movimentacao_Geral[[#This Row],[Status Financeiro]] ) -> Pago | L41: =IF( $O$7="Desbloqueado", CHOOSE(RANDBETWEEN(1,3),"Entregue","Em Rota","Aguardando"), Tabela_Movimentacao_Geral[[#This Row],[Status Logistico]] ) -> Em Rota | M41: =IF( $O$7="Desbloqueado", IF( Tabela_Movimentacao_Geral[[#This Row],[Tipo Fluxo]]="Entrada", Tabela_Movimentacao_Geral[[#This Row],[Data]] + _xlfn.XLOOKUP(Tabela_Movimentacao_Geral[[#This Row],[ID Entidade]],Tabela_Fornecedores[ID_Fornecedor],Tabela_Fornecedores[Lead_Time]), "N/A" ), Tabela_Movimentacao_Geral[[#This Row],[Previsão de Entrega]] ) -> 45686
A42: ="T"&TEXT(ROW(A42)-1,"0000") -> T0041 | B42: 45683 | C42: {=IF($O$7="Desbloqueado", _xlfn.LET( _xlpm.saldo_atual, SUM(($C$2:$C41="Entrada")*($F$2:$F41=Tabela_Movimentacao_Geral[[#This Row],[ID Produto]])*($H$2:$H41) - ($C$2:$C41="Saida")*($F$2:$F41=Tabela_Movimentacao_Geral[[#This Row],[ID Produto]])*($H$2:$H41)), IF(_xlpm.saldo_atual > 0, IF(RANDBETWEEN(0,10)>3,"Saida","Entrada"), "Entrada") ), Tabela_Movimentacao_Geral[[#This Row],[Tipo Fluxo]] )} -> Entrada | D42: =IF( $O$7="Desbloqueado", IF( Tabela_Movimentacao_Geral[[#This Row],[Tipo Fluxo]]="Saida", "CLI"&TEXT(RANDBETWEEN(1,20),"000"), "FORN"&TEXT(RANDBETWEEN(1,20),"000") ), Tabela_Movimentacao_Geral[[#This Row],[ID Entidade]] ) -> FORN010 | E42: =IF(Tabela_Movimentacao_Geral[[#This Row],[Tipo Fluxo]]="Saida",_xlfn.XLOOKUP(Tabela_Movimentacao_Geral[[#This Row],[ID Entidade]], Tabela_Clientes[ID_Cliente],Tabela_Clientes[Nome_Cliente],"Cliente não encontrado"),_xlfn.XLOOKUP(Tabela_Movimentacao_Geral[[#This Row],[ID Entidade]], Tabela_Fornecedores[ID_Fornecedor], Tabela_Fornecedores[Nome_Fantasia], "Fornecedor não encontrado")) -> DataCenter Pro | F42: =IF( $O$7="Desbloqueado", "PROD"&TEXT(RANDBETWEEN(1,200),"000"), Tabela_Movimentacao_Geral[[#This Row],[ID Produto]] ) -> PROD199 | G42: =_xlfn.XLOOKUP(Tabela_Movimentacao_Geral[[#This Row],[ID Produto]], Tabela_Produtos[ID_Produto],Tabela_Produtos[Descricao_Produto],"Produto não encontrado") -> Sugador de Solda | H42: {=IF( $O$7="Desbloqueado", _xlfn.LET( _xlpm.saldo_atual, SUM(($C$2:$C41="Entrada")*($F$2:$F41=Tabela_Movimentacao_Geral[[#This Row],[ID Produto]])*($H$2:$H41) - ($C$2:$C41="Saida")*($F$2:$F41=Tabela_Movimentacao_Geral[[#This Row],[ID Produto]])*($H$2:$H41)), _xlpm.estoque_minimo, _xlfn.XLOOKUP(Tabela_Movimentacao_Geral[[#This Row],[ID Produto]], Tabela_Produtos[ID_Produto], Tabela_Produtos[Estoque_Minimo], 0), IF( _xlpm.saldo_atual > _xlpm.estoque_minimo, IF( Tabela_Movimentacao_Geral[[#This Row],[Tipo Fluxo]]="Saida", RANDBETWEEN(1, _xlpm.saldo_atual), RANDBETWEEN(1, 100) ), IF( Tabela_Movimentacao_Geral[[#This Row],[Tipo Fluxo]]="Saida", RANDBETWEEN(1, _xlpm.saldo_atual), IF( _xlpm.saldo_atual < 0, ABS(_xlpm.saldo_atual) + _xlpm.estoque_minimo + RANDBETWEEN(1, 100), _xlpm.estoque_minimo - _xlpm.saldo_atual + RANDBETWEEN(1, 100) ) ) ) ), Tabela_Movimentacao_Geral[[#This Row],[Quantidade]] )} -> 108 | I42: =_xlfn.XLOOKUP(Tabela_Movimentacao_Geral[[#This Row],[ID Produto]], Tabela_Produtos[ID_Produto],Tabela_Produtos[Preco_Unitario_Venda]) -> 25 | J42: =Tabela_Movimentacao_Geral[[#This Row],[Quantidade]] * Tabela_Movimentacao_Geral[[#This Row],[Valor Unitário]] -> 2700 | K42: =IF( $O$7="Desbloqueado", CHOOSE(RANDBETWEEN(1,3),"Pago","Pendente","Atrasado"), Tabela_Movimentacao_Geral[[#This Row],[Status Financeiro]] ) -> Pago | L42: =IF( $O$7="Desbloqueado", CHOOSE(RANDBETWEEN(1,3),"Entregue","Em Rota","Aguardando"), Tabela_Movimentacao_Geral[[#This Row],[Status Logistico]] ) -> Em Rota | M42: =IF( $O$7="Desbloqueado", IF( Tabela_Movimentacao_Geral[[#This Row],[Tipo Fluxo]]="Entrada", Tabela_Movimentacao_Geral[[#This Row],[Data]] + _xlfn.XLOOKUP(Tabela_Movimentacao_Geral[[#This Row],[ID Entidade]],Tabela_Fornecedores[ID_Fornecedor],Tabela_Fornecedores[Lead_Time]), "N/A" ), Tabela_Movimentacao_Geral[[#This Row],[Previsão de Entrega]] ) -> 45685
... A1021: ="T"&TEXT(ROW(A1021)-1,"0000") -> T1020 | B1021: 46144 | C1021: {=IF($O$7="Desbloqueado", _xlfn.LET( _xlpm.saldo_atual, SUM(($C$2:$C1020="Entrada")*($F$2:$F1020=Tabela_Movimentacao_Geral[[#This Row],[ID Produto]])*($H$2:$H1020) - ($C$2:$C1020="Saida")*($F$2:$F1020=Tabela_Movimentacao_Geral[[#This Row],[ID Produto]])*($H$2:$H1020)), IF(_xlpm.saldo_atual > 0, IF(RANDBETWEEN(0,10)>3,"Saida","Entrada"), "Entrada") ), Tabela_Movimentacao_Geral[[#This Row],[Tipo Fluxo]] )} -> Saida | D1021: =IF( $O$7="Desbloqueado", IF( Tabela_Movimentacao_Geral[[#This Row],[Tipo Fluxo]]="Saida", "CLI"&TEXT(RANDBETWEEN(1,20),"000"), "FORN"&TEXT(RANDBETWEEN(1,20),"000") ), Tabela_Movimentacao_Geral[[#This Row],[ID Entidade]] ) -> CLI001 | E1021: =IF(Tabela_Movimentacao_Geral[[#This Row],[Tipo Fluxo]]="Saida",_xlfn.XLOOKUP(Tabela_Movimentacao_Geral[[#This Row],[ID Entidade]], Tabela_Clientes[ID_Cliente],Tabela_Clientes[Nome_Cliente],"Cliente não encontrado"),_xlfn.XLOOKUP(Tabela_Movimentacao_Geral[[#This Row],[ID Entidade]], Tabela_Fornecedores[ID_Fornecedor], Tabela_Fornecedores[Nome_Fantasia], "Fornecedor não encontrado")) -> Industrias Alpha | F1021: =IF( $O$7="Desbloqueado", "PROD"&TEXT(RANDBETWEEN(1,200),"000"), Tabela_Movimentacao_Geral[[#This Row],[ID Produto]] ) -> PROD075 | G1021: =_xlfn.XLOOKUP(Tabela_Movimentacao_Geral[[#This Row],[ID Produto]], Tabela_Produtos[ID_Produto],Tabela_Produtos[Descricao_Produto],"Produto não encontrado") -> Suporte de Pasta Acrilico | H1021: {=IF( $O$7="Desbloqueado", _xlfn.LET( _xlpm.saldo_atual, SUM(($C$2:$C1020="Entrada")*($F$2:$F1020=Tabela_Movimentacao_Geral[[#This Row],[ID Produto]])*($H$2:$H1020) - ($C$2:$C1020="Saida")*($F$2:$F1020=Tabela_Movimentacao_Geral[[#This Row],[ID Produto]])*($H$2:$H1020)), _xlpm.estoque_minimo, _xlfn.XLOOKUP(Tabela_Movimentacao_Geral[[#This Row],[ID Produto]], Tabela_Produtos[ID_Produto], Tabela_Produtos[Estoque_Minimo], 0), IF( _xlpm.saldo_atual > _xlpm.estoque_minimo, IF( Tabela_Movimentacao_Geral[[#This Row],[Tipo Fluxo]]="Saida", RANDBETWEEN(1, _xlpm.saldo_atual), RANDBETWEEN(1, 100) ), IF( Tabela_Movimentacao_Geral[[#This Row],[Tipo Fluxo]]="Saida", RANDBETWEEN(1, _xlpm.saldo_atual), IF( _xlpm.saldo_atual < 0, ABS(_xlpm.saldo_atual) + _xlpm.estoque_minimo + RANDBETWEEN(1, 100), _xlpm.estoque_minimo - _xlpm.saldo_atual + RANDBETWEEN(1, 100) ) ) ) ), Tabela_Movimentacao_Geral[[#This Row],[Quantidade]] )} -> 1 | I1021: =_xlfn.XLOOKUP(Tabela_Movimentacao_Geral[[#This Row],[ID Produto]], Tabela_Produtos[ID_Produto],Tabela_Produtos[Preco_Unitario_Venda]) -> 38 | J1021: =Tabela_Movimentacao_Geral[[#This Row],[Quantidade]] * Tabela_Movimentacao_Geral[[#This Row],[Valor Unitário]] -> 38 | K1021: =IF( $O$7="Desbloqueado", CHOOSE(RANDBETWEEN(1,3),"Pago","Pendente","Atrasado"), Tabela_Movimentacao_Geral[[#This Row],[Status Financeiro]] ) -> Pago | L1021: =IF( $O$7="Desbloqueado", CHOOSE(RANDBETWEEN(1,3),"Entregue","Em Rota","Aguardando"), Tabela_Movimentacao_Geral[[#This Row],[Status Logistico]] ) -> Em Rota | M1021: =IF( $O$7="Desbloqueado", IF( Tabela_Movimentacao_Geral[[#This Row],[Tipo Fluxo]]="Entrada", Tabela_Movimentacao_Geral[[#This Row],[Data]] + _xlfn.XLOOKUP(Tabela_Movimentacao_Geral[[#This Row],[ID Entidade]],Tabela_Fornecedores[ID_Fornecedor],Tabela_Fornecedores[Lead_Time]), "N/A" ), Tabela_Movimentacao_Geral[[#This Row],[Previsão de Entrega]] ) -> N/A

Sheet AUX_CADASTROS
A1: ID_Cliente | B1: Nome_Cliente | C1: CPF_CNPJ | D1: Limite_Credito | F1: ID_Fornecedor | G1: Nome_Fantasia | H1: CNPJ | I1: Categoria | J1: Lead_Time | L1: ID_Produto | M1: Descricao_Produto | N1: Preco_Unitario_Venda | O1: Estoque_Minimo
A2: CLI001 | B2: Industrias Alpha | C2: 10.100.100/0001-01 | D2: 50000 | F2: FORN001 | G2: TechFlow Solucoes | H2: 12.345.678/0001-01 | I2: Hardware | J2: 5 | L2: PROD001 | M2: Monitor 24 pol Full HD | N2: 850 | O2: 10
A3: CLI002 | B3: Varejo Total | C3: 20.200.200/0001-02 | D3: 15000 | F3: FORN002 | G3: SoftPrime Licencas | H3: 23.456.789/0001-02 | I3: Software | J3: 1 | L3: PROD002 | M3: Teclado Mecanico RGB | N3: 350 | O3: 15
A4: CLI003 | B4: Hospital Vida | C4: 30.300.300/0001-03 | D4: 80000 | F4: FORN003 | G4: Office Express | H4: 34.567.890/0001-03 | I4: Suprimentos | J4: 2 | L4: PROD003 | M4: Mouse Sem Fio Optico | N4: 120 | O4: 30
A5: CLI004 | B5: Escola Saber | C5: 40.400.400/0001-04 | D5: 10000 | F5: FORN004 | G5: LogiBrasil Transportes | H5: 45.678.901/0001-04 | I5: Logistica | J5: 3 | L5: PROD004 | M5: Cadeira Ergonomica Office | N5: 1200 | O5: 5
A6: CLI005 | B6: Banco Futuro | C6: 50.500.500/0001-05 | D6: 200000 | F6: FORN005 | G6: CloudNexus Data | H6: 56.789.012/0001-05 | I6: Infraestrutura | J6: 1 | L6: PROD005 | M6: Notebook i5 8GB 256GB SSD | N6: 3500 | O6: 8
A7: CLI006 | B7: Construtora Forte | C7: 60.600.600/0001-06 | D7: 120000 | F7: FORN006 | G7: Papelaria Central | H7: 67.890.123/0001-06 | I7: Suprimentos | J7: 2 | L7: PROD006 | M7: Notebook i7 16GB 512GB SSD | N7: 5500 | O7: 4
A8: CLI007 | B8: Tecno Logica | C8: 70.700.700/0001-07 | D8: 45000 | F8: FORN007 | G8: CyberSecurity SA | H8: 78.901.234/0001-07 | I8: Seguranca | J8: 7 | L8: PROD007 | M8: Impressora Laser Color | N8: 1800 | O8: 3
A9: CLI008 | B9: Supermercado Sol | C9: 80.800.800/0001-08 | D9: 30000 | F9: FORN008 | G9: Global Chips | H9: 89.012.345/0001-08 | I9: Hardware | J9: 15 | L9: PROD008 | M9: Toner Preto High Yield | N9: 250 | O9: 20
A10: CLI009 | B10: Farma Plus | C10: 90.900.900/0001-09 | D10: 25000 | F10: FORN009 | G10: Movel Tech | H10: 90.123.456/0001-09 | I10: Infraestrutura | J10: 10 | L10: PROD009 | M10: Cabo HDMI 2.0 2m | N10: 45 | O10: 50
A11: CLI010 | B11: Hotel Estrela | C11: 01.010.010/0001-10 | D11: 60000 | F11: FORN010 | G11: DataCenter Pro | H11: 01.234.567/0001-10 | I11: Software | J11: 2 | L11: PROD010 | M11: SSD 480GB SATA3 | N11: 320 | O11: 25
A12: CLI011 | B12: Academia Fit | C12: 11.111.111/0001-11 | D12: 5000 | F12: FORN011 | G12: Energy Solution | H12: 11.222.333/0001-11 | I12: Suprimentos | J12: 4 | L12: PROD011 | M12: Memoria RAM 8GB DDR4 | N12: 280 | O12: 15
A13: CLI012 | B13: Padaria Real | C13: 22.222.222/0001-22 | D13: 3000 | F13: FORN012 | G13: Fast Delivery | H13: 22.333.444/0001-12 | I13: Logistica | J13: 1 | L13: PROD012 | M13: Webcam 1080p Business | N13: 450 | O13: 12
... A21: CLI020 | B21: Oficina Mecanica | C21: 00.000.000/0001-00 | D21: 10000 | F21: FORN020 | G21: AI Systems | H21: 00.111.222/0001-20 | I21: Software | J21: 1 | L21: PROD020 | M21: Estabilizador 1000VA | N21: 400 | O21: 6
L22: PROD021 | M22: Pacote Office Business Anual | N22: 599 | O22: 100
L23: PROD022 | M23: Licenca Windows 11 Pro | N23: 980 | O23: 100
L24: PROD023 | M24: Antivirus Endpoint 1 Ano | N24: 150 | O24: 200
L25: PROD024 | M25: Assinatura Adobe CC Anual | N25: 2400 | O25: 50
L26: PROD025 | M26: Software de Backup Cloud | N26: 85 | O26: 100
L27: PROD026 | M27: Mousepad Gamer Extra Large | N27: 85 | O27: 25
L28: PROD027 | M28: Hub USB 3.0 4 Portas | N28: 75 | O28: 30
L29: PROD028 | M29: Cabo de Rede Cat6 3m | N29: 25 | O29: 60
L30: PROD029 | M30: Caneta Digital para Tablet | N30: 320 | O30: 10
L31: PROD030 | M31: Mochila para Notebook 15.6 | N31: 250 | O31: 15
L32: PROD031 | M32: Nobreak 1500VA Biz | N32: 1450 | O32: 4
L33: PROD032 | M33: Base Resfriadora Notebook | N33: 110 | O33: 20
... L201: PROD200 | M201: Estacao de Solda Prof | N201: 1200 | O201: 3

Sheet CONTROLE_ESTOQUE
A1: ID_Produto | B1: Descricao_Produto | C1: Estoque_Minimo | D1: Entradas | E1: Saídas | F1: Saldo Atual | G1: Status de Reposição
A2: PROD001 | B2: =_xlfn.XLOOKUP(Tabela_Controle_Estoque[[#This Row],[ID_Produto]],Tabela_Produtos[ID_Produto],Tabela_Produtos[Descricao_Produto],"N/A") -> Monitor 24 pol Full HD | C2: =_xlfn.XLOOKUP(Tabela_Controle_Estoque[[#This Row],[ID_Produto]],Tabela_Produtos[ID_Produto],Tabela_Produtos[Estoque_Minimo],"N/A") -> 10 | D2: =SUMIFS(Tabela_Movimentacao_Geral[Quantidade],Tabela_Movimentacao_Geral[ID Produto],CONTROLE_ESTOQUE!$A2,Tabela_Movimentacao_Geral[Tipo Fluxo], "Entrada") -> 179 | E2: =SUMIFS(Tabela_Movimentacao_Geral[Quantidade], Tabela_Movimentacao_Geral[ID Produto],CONTROLE_ESTOQUE!$A2,Tabela_Movimentacao_Geral[Tipo Fluxo], "Saida") -> 18 | F2: =CONTROLE_ESTOQUE!$D2 - CONTROLE_ESTOQUE!$E2 -> 161 | G2: =IF(CONTROLE_ESTOQUE!$F2 < CONTROLE_ESTOQUE!$C2, "COMPRAR URGENTE", "Estoque OK") -> Estoque OK
A3: PROD002 | B3: =_xlfn.XLOOKUP(Tabela_Controle_Estoque[[#This Row],[ID_Produto]],Tabela_Produtos[ID_Produto],Tabela_Produtos[Descricao_Produto],"N/A") -> Teclado Mecanico RGB | C3: =_xlfn.XLOOKUP(Tabela_Controle_Estoque[[#This Row],[ID_Produto]],Tabela_Produtos[ID_Produto],Tabela_Produtos[Estoque_Minimo],"N/A") -> 15 | D3: =SUMIFS(Tabela_Movimentacao_Geral[Quantidade],Tabela_Movimentacao_Geral[ID Produto],CONTROLE_ESTOQUE!$A3,Tabela_Movimentacao_Geral[Tipo Fluxo], "Entrada") -> 107 | E3: =SUMIFS(Tabela_Movimentacao_Geral[Quantidade], Tabela_Movimentacao_Geral[ID Produto],CONTROLE_ESTOQUE!$A3,Tabela_Movimentacao_Geral[Tipo Fluxo], "Saida") -> 89 | F3: =CONTROLE_ESTOQUE!$D3 - CONTROLE_ESTOQUE!$E3 -> 18 | G3: =IF(CONTROLE_ESTOQUE!$F3 < CONTROLE_ESTOQUE!$C3, "COMPRAR URGENTE", "Estoque OK") -> Estoque OK
A4: PROD003 | B4: =_xlfn.XLOOKUP(Tabela_Controle_Estoque[[#This Row],[ID_Produto]],Tabela_Produtos[ID_Produto],Tabela_Produtos[Descricao_Produto],"N/A") -> Mouse Sem Fio Optico | C4: =_xlfn.XLOOKUP(Tabela_Controle_Estoque[[#This Row],[ID_Produto]],Tabela_Produtos[ID_Produto],Tabela_Produtos[Estoque_Minimo],"N/A") -> 30 | D4: =SUMIFS(Tabela_Movimentacao_Geral[Quantidade],Tabela_Movimentacao_Geral[ID Produto],CONTROLE_ESTOQUE!$A4,Tabela_Movimentacao_Geral[Tipo Fluxo], "Entrada") -> 227 | E4: =SUMIFS(Tabela_Movimentacao_Geral[Quantidade], Tabela_Movimentacao_Geral[ID Produto],CONTROLE_ESTOQUE!$A4,Tabela_Movimentacao_Geral[Tipo Fluxo], "Saida") -> 156 | F4: =CONTROLE_ESTOQUE!$D4 - CONTROLE_ESTOQUE!$E4 -> 71 | G4: =IF(CONTROLE_ESTOQUE!$F4 < CONTROLE_ESTOQUE!$C4, "COMPRAR URGENTE", "Estoque OK") -> Estoque OK
A5: PROD004 | B5: =_xlfn.XLOOKUP(Tabela_Controle_Estoque[[#This Row],[ID_Produto]],Tabela_Produtos[ID_Produto],Tabela_Produtos[Descricao_Produto],"N/A") -> Cadeira Ergonomica Office | C5: =_xlfn.XLOOKUP(Tabela_Controle_Estoque[[#This Row],[ID_Produto]],Tabela_Produtos[ID_Produto],Tabela_Produtos[Estoque_Minimo],"N/A") -> 5 | D5: =SUMIFS(Tabela_Movimentacao_Geral[Quantidade],Tabela_Movimentacao_Geral[ID Produto],CONTROLE_ESTOQUE!$A5,Tabela_Movimentacao_Geral[Tipo Fluxo], "Entrada") -> 157 | E5: =SUMIFS(Tabela_Movimentacao_Geral[Quantidade], Tabela_Movimentacao_Geral[ID Produto],CONTROLE_ESTOQUE!$A5,Tabela_Movimentacao_Geral[Tipo Fluxo], "Saida") -> 130 | F5: =CONTROLE_ESTOQUE!$D5 - CONTROLE_ESTOQUE!$E5 -> 27 | G5: =IF(CONTROLE_ESTOQUE!$F5 < CONTROLE_ESTOQUE!$C5, "COMPRAR URGENTE", "Estoque OK") -> Estoque OK
A6: PROD005 | B6: =_xlfn.XLOOKUP(Tabela_Controle_Estoque[[#This Row],[ID_Produto]],Tabela_Produtos[ID_Produto],Tabela_Produtos[Descricao_Produto],"N/A") -> Notebook i5 8GB 256GB SSD | C6: =_xlfn.XLOOKUP(Tabela_Controle_Estoque[[#This Row],[ID_Produto]],Tabela_Produtos[ID_Produto],Tabela_Produtos[Estoque_Minimo],"N/A") -> 8 | D6: =SUMIFS(Tabela_Movimentacao_Geral[Quantidade],Tabela_Movimentacao_Geral[ID Produto],CONTROLE_ESTOQUE!$A6,Tabela_Movimentacao_Geral[Tipo Fluxo], "Entrada") -> 25 | E6: =SUMIFS(Tabela_Movimentacao_Geral[Quantidade], Tabela_Movimentacao_Geral[ID Produto],CONTROLE_ESTOQUE!$A6,Tabela_Movimentacao_Geral[Tipo Fluxo], "Saida") -> 13 | F6: =CONTROLE_ESTOQUE!$D6 - CONTROLE_ESTOQUE!$E6 -> 12 | G6: =IF(CONTROLE_ESTOQUE!$F6 < CONTROLE_ESTOQUE!$C6, "COMPRAR URGENTE", "Estoque OK") -> Estoque OK
A7: PROD006 | B7: =_xlfn.XLOOKUP(Tabela_Controle_Estoque[[#This Row],[ID_Produto]],Tabela_Produtos[ID_Produto],Tabela_Produtos[Descricao_Produto],"N/A") -> Notebook i7 16GB 512GB SSD | C7: =_xlfn.XLOOKUP(Tabela_Controle_Estoque[[#This Row],[ID_Produto]],Tabela_Produtos[ID_Produto],Tabela_Produtos[Estoque_Minimo],"N/A") -> 4 | D7: =SUMIFS(Tabela_Movimentacao_Geral[Quantidade],Tabela_Movimentacao_Geral[ID Produto],CONTROLE_ESTOQUE!$A7,Tabela_Movimentacao_Geral[Tipo Fluxo], "Entrada") -> 96 | E7: =SUMIFS(Tabela_Movimentacao_Geral[Quantidade], Tabela_Movimentacao_Geral[ID Produto],CONTROLE_ESTOQUE!$A7,Tabela_Movimentacao_Geral[Tipo Fluxo], "Saida") -> 75 | F7: =CONTROLE_ESTOQUE!$D7 - CONTROLE_ESTOQUE!$E7 -> 21 | G7: =IF(CONTROLE_ESTOQUE!$F7 < CONTROLE_ESTOQUE!$C7, "COMPRAR URGENTE", "Estoque OK") -> Estoque OK
A8: PROD007 | B8: =_xlfn.XLOOKUP(Tabela_Controle_Estoque[[#This Row],[ID_Produto]],Tabela_Produtos[ID_Produto],Tabela_Produtos[Descricao_Produto],"N/A") -> Impressora Laser Color | C8: =_xlfn.XLOOKUP(Tabela_Controle_Estoque[[#This Row],[ID_Produto]],Tabela_Produtos[ID_Produto],Tabela_Produtos[Estoque_Minimo],"N/A") -> 3 | D8: =SUMIFS(Tabela_Movimentacao_Geral[Quantidade],Tabela_Movimentacao_Geral[ID Produto],CONTROLE_ESTOQUE!$A8,Tabela_Movimentacao_Geral[Tipo Fluxo], "Entrada") -> 57 | E8: =SUMIFS(Tabela_Movimentacao_Geral[Quantidade], Tabela_Movimentacao_Geral[ID Produto],CONTROLE_ESTOQUE!$A8,Tabela_Movimentacao_Geral[Tipo Fluxo], "Saida") -> 56 | F8: =CONTROLE_ESTOQUE!$D8 - CONTROLE_ESTOQUE!$E8 -> 1 | G8: =IF(CONTROLE_ESTOQUE!$F8 < CONTROLE_ESTOQUE!$C8, "COMPRAR URGENTE", "Estoque OK") -> COMPRAR URGENTE
A9: PROD008 | B9: =_xlfn.XLOOKUP(Tabela_Controle_Estoque[[#This Row],[ID_Produto]],Tabela_Produtos[ID_Produto],Tabela_Produtos[Descricao_Produto],"N/A") -> Toner Preto High Yield | C9: =_xlfn.XLOOKUP(Tabela_Controle_Estoque[[#This Row],[ID_Produto]],Tabela_Produtos[ID_Produto],Tabela_Produtos[Estoque_Minimo],"N/A") -> 20 | D9: =SUMIFS(Tabela_Movimentacao_Geral[Quantidade],Tabela_Movimentacao_Geral[ID Produto],CONTROLE_ESTOQUE!$A9,Tabela_Movimentacao_Geral[Tipo Fluxo], "Entrada") -> 53 | E9: =SUMIFS(Tabela_Movimentacao_Geral[Quantidade], Tabela_Movimentacao_Geral[ID Produto],CONTROLE_ESTOQUE!$A9,Tabela_Movimentacao_Geral[Tipo Fluxo], "Saida") -> 46 | F9: =CONTROLE_ESTOQUE!$D9 - CONTROLE_ESTOQUE!$E9 -> 7 | G9: =IF(CONTROLE_ESTOQUE!$F9 < CONTROLE_ESTOQUE!$C9, "COMPRAR URGENTE", "Estoque OK") -> COMPRAR URGENTE
A10: PROD009 | B10: =_xlfn.XLOOKUP(Tabela_Controle_Estoque[[#This Row],[ID_Produto]],Tabela_Produtos[ID_Produto],Tabela_Produtos[Descricao_Produto],"N/A") -> Cabo HDMI 2.0 2m | C10: =_xlfn.XLOOKUP(Tabela_Controle_Estoque[[#This Row],[ID_Produto]],Tabela_Produtos[ID_Produto],Tabela_Produtos[Estoque_Minimo],"N/A") -> 50 | D10: =SUMIFS(Tabela_Movimentacao_Geral[Quantidade],Tabela_Movimentacao_Geral[ID Produto],CONTROLE_ESTOQUE!$A10,Tabela_Movimentacao_Geral[Tipo Fluxo], "Entrada") -> 226 | E10: =SUMIFS(Tabela_Movimentacao_Geral[Quantidade], Tabela_Movimentacao_Geral[ID Produto],CONTROLE_ESTOQUE!$A10,Tabela_Movimentacao_Geral[Tipo Fluxo], "Saida") -> 180 | F10: =CONTROLE_ESTOQUE!$D10 - CONTROLE_ESTOQUE!$E10 -> 46 | G10: =IF(CONTROLE_ESTOQUE!$F10 < CONTROLE_ESTOQUE!$C10, "COMPRAR URGENTE", "Estoque OK") -> COMPRAR URGENTE
A11: PROD010 | B11: =_xlfn.XLOOKUP(Tabela_Controle_Estoque[[#This Row],[ID_Produto]],Tabela_Produtos[ID_Produto],Tabela_Produtos[Descricao_Produto],"N/A") -> SSD 480GB SATA3 | C11: =_xlfn.XLOOKUP(Tabela_Controle_Estoque[[#This Row],[ID_Produto]],Tabela_Produtos[ID_Produto],Tabela_Produtos[Estoque_Minimo],"N/A") -> 25 | D11: =SUMIFS(Tabela_Movimentacao_Geral[Quantidade],Tabela_Movimentacao_Geral[ID Produto],CONTROLE_ESTOQUE!$A11,Tabela_Movimentacao_Geral[Tipo Fluxo], "Entrada") -> 83 | E11: =SUMIFS(Tabela_Movimentacao_Geral[Quantidade], Tabela_Movimentacao_Geral[ID Produto],CONTROLE_ESTOQUE!$A11,Tabela_Movimentacao_Geral[Tipo Fluxo], "Saida") -> 50 | F11: =CONTROLE_ESTOQUE!$D11 - CONTROLE_ESTOQUE!$E11 -> 33 | G11: =IF(CONTROLE_ESTOQUE!$F11 < CONTROLE_ESTOQUE!$C11, "COMPRAR URGENTE", "Estoque OK") -> Estoque OK
A12: PROD011 | B12: =_xlfn.XLOOKUP(Tabela_Controle_Estoque[[#This Row],[ID_Produto]],Tabela_Produtos[ID_Produto],Tabela_Produtos[Descricao_Produto],"N/A") -> Memoria RAM 8GB DDR4 | C12: =_xlfn.XLOOKUP(Tabela_Controle_Estoque[[#This Row],[ID_Produto]],Tabela_Produtos[ID_Produto],Tabela_Produtos[Estoque_Minimo],"N/A") -> 15 | D12: =SUMIFS(Tabela_Movimentacao_Geral[Quantidade],Tabela_Movimentacao_Geral[ID Produto],CONTROLE_ESTOQUE!$A12,Tabela_Movimentacao_Geral[Tipo Fluxo], "Entrada") -> 179 | E12: =SUMIFS(Tabela_Movimentacao_Geral[Quantidade], Tabela_Movimentacao_Geral[ID Produto],CONTROLE_ESTOQUE!$A12,Tabela_Movimentacao_Geral[Tipo Fluxo], "Saida") -> 89 | F12: =CONTROLE_ESTOQUE!$D12 - CONTROLE_ESTOQUE!$E12 -> 90 | G12: =IF(CONTROLE_ESTOQUE!$F12 < CONTROLE_ESTOQUE!$C12, "COMPRAR URGENTE", "Estoque OK") -> Estoque OK
A13: PROD012 | B13: =_xlfn.XLOOKUP(Tabela_Controle_Estoque[[#This Row],[ID_Produto]],Tabela_Produtos[ID_Produto],Tabela_Produtos[Descricao_Produto],"N/A") -> Webcam 1080p Business | C13: =_xlfn.XLOOKUP(Tabela_Controle_Estoque[[#This Row],[ID_Produto]],Tabela_Produtos[ID_Produto],Tabela_Produtos[Estoque_Minimo],"N/A") -> 12 | D13: =SUMIFS(Tabela_Movimentacao_Geral[Quantidade],Tabela_Movimentacao_Geral[ID Produto],CONTROLE_ESTOQUE!$A13,Tabela_Movimentacao_Geral[Tipo Fluxo], "Entrada") -> 42 | E13: =SUMIFS(Tabela_Movimentacao_Geral[Quantidade], Tabela_Movimentacao_Geral[ID Produto],CONTROLE_ESTOQUE!$A13,Tabela_Movimentacao_Geral[Tipo Fluxo], "Saida") -> 33 | F13: =CONTROLE_ESTOQUE!$D13 - CONTROLE_ESTOQUE!$E13 -> 9 | G13: =IF(CONTROLE_ESTOQUE!$F13 < CONTROLE_ESTOQUE!$C13, "COMPRAR URGENTE", "Estoque OK") -> COMPRAR URGENTE
... A201: PROD200 | B201: =_xlfn.XLOOKUP(Tabela_Controle_Estoque[[#This Row],[ID_Produto]],Tabela_Produtos[ID_Produto],Tabela_Produtos[Descricao_Produto],"N/A") -> Estacao de Solda Prof | C201: =_xlfn.XLOOKUP(Tabela_Controle_Estoque[[#This Row],[ID_Produto]],Tabela_Produtos[ID_Produto],Tabela_Produtos[Estoque_Minimo],"N/A") -> 3 | D201: =SUMIFS(Tabela_Movimentacao_Geral[Quantidade],Tabela_Movimentacao_Geral[ID Produto],CONTROLE_ESTOQUE!$A201,Tabela_Movimentacao_Geral[Tipo Fluxo], "Entrada") -> 165 | E201: =SUMIFS(Tabela_Movimentacao_Geral[Quantidade], Tabela_Movimentacao_Geral[ID Produto],CONTROLE_ESTOQUE!$A201,Tabela_Movimentacao_Geral[Tipo Fluxo], "Saida") -> 38 | F201: =CONTROLE_ESTOQUE!$D201 - CONTROLE_ESTOQUE!$E201 -> 127 | G201: =IF(CONTROLE_ESTOQUE!$F201 < CONTROLE_ESTOQUE!$C201, "COMPRAR URGENTE", "Estoque OK") -> Estoque OK

Sheet CALCULUS
H1: Tipo Fluxo | I1: (Tudo)
A3: Tipo Fluxo | B3: (Tudo) | H3: Rótulos de Linha | I3: Soma de Valor Total | S3: Tipo Fluxo | T3: (Tudo)
H4: Jan | I4: 2472515.5
A5: Rótulos de Linha | B5: Soma de Valor Total | H5: Feb | I5: 3714283.5 | S5: Rótulos de Linha | T5: Soma de Valor Total
A6: Pendente | B6: 9530099 | H6: Mar | I6: 4557761 | S6: Unidade LTO-8 Backup | T6: 4424000
A7: Pago | B7: 12729245 | H7: Apr | I7: 5348226.5 | S7: Firewall Hardware Mid | T7: 2023000
A8: Atrasado | B8: 9375288 | H8: May | I8: 2254123.5 | S8: Servidor Rack 1U | T8: 2012500
A9: Total Geral | B9: 31634632 | H9: Jun | I9: 1429261.5 | S9: KVM Console Gaveta 17 | T9: 1978800
H10: Jul | I10: 2326359.5 | S10: Assinatura Adobe CC Anual | T10: 1317600
A11: =B3 -> (Tudo) | B11: =GETPIVOTDATA("Valor Total",$A$5) -> 31634632 | H11: Aug | I11: 1505276.5 | S11: Total Geral | T11: 11755900
H12: Sep | I12: 604122
A13: =IF(CALCULUS!$A$11="Saida","Fluxo de Caixa (Saída)", IF(CALCULUS!$A$11="Entrada", "Fluxo de Caixa (Entrada)", "Fluxo de Caixa (Total)")) -> Fluxo de Caixa (Total) | H13: Oct | I13: 3713712.5
H14: Nov | I14: 1276103.5 | S14: =IF(CALCULUS!$A$11="Saida","Ranking de Receita por Produto (Saídas)", IF(CALCULUS!$A$11="Entrada", "Ranking de Receita por Produto (Entradas)", "Ranking de Receita por Produto (Total)")) -> Ranking de Receita por Produto (Total)
H15: Dec | I15: 2432886.5
H16: Total Geral | I16: 31634632
H18: =IF(CALCULUS!$A$11="Saida","Evolução do Faturamento Mensal (Saídas)", IF(CALCULUS!$A$11="Entrada", "Evolução do Faturamento Mensal (Entradas)","Evolução do Faturamento Mensal (Total)")) -> Evolução do Faturamento Mensal (Total)
C19: Faturamento | D19: Inadiplência | E19: Contas a Receber | F19: Total Saida
C20: =SUMIFS(Tabela_Movimentacao_Geral[Valor Total],Tabela_Movimentacao_Geral[Tipo Fluxo], "Saida", Tabela_Movimentacao_Geral[Status Financeiro], "Pago") -> 3393774.5 | D20: =SUMIFS(Tabela_Movimentacao_Geral[Valor Total], Tabela_Movimentacao_Geral[Tipo Fluxo], "Saida", Tabela_Movimentacao_Geral[Status Financeiro], "Atrasado") -> 2854062.5 | E20: =SUMIFS(Tabela_Movimentacao_Geral[Valor Total], Tabela_Movimentacao_Geral[Tipo Fluxo], "Saida", Tabela_Movimentacao_Geral[Status Financeiro], "Pendente") -> 3692572.5 | F20: =SUM(Dashboard[[#This Row],[Faturamento ]:[Contas a Receber]]) -> 9940409.5
C21: Faturamento | D21: Inadiplência | E21: Contas a Receber | F21: Total Saida
C22: =SUMIFS(Tabela_Movimentacao_Geral[Valor Total],Tabela_Movimentacao_Geral[Tipo Fluxo], "Entrada", Tabela_Movimentacao_Geral[Status Financeiro], "Pago") -> 9335470.5 | D22: =SUMIFS(Tabela_Movimentacao_Geral[Valor Total], Tabela_Movimentacao_Geral[Tipo Fluxo], "Entrada", Tabela_Movimentacao_Geral[Status Financeiro], "Atrasado") -> 6521225.5 | E22: =SUMIFS(Tabela_Movimentacao_Geral[Valor Total], Tabela_Movimentacao_Geral[Tipo Fluxo], "Entrada", Tabela_Movimentacao_Geral[Status Financeiro], "Pendente") -> 5837526.5 | F22: =SUM(Dashboard2[[#This Row],[Faturamento]:[Contas a Receber]]) -> 21694222 | J22: Rótulos de Linha | K22: Contagem de ID_Produto
J23: COMPRAR URGENTE | K23: 57
C24: Ctrl + Alt + F5 (Atualiza todas as conexões e tabelas do arquivo de uma vez só). | J24: Estoque OK | K24: 143
J25: Total Geral | K25: 200
K27: =GETPIVOTDATA("ID_Produto",$J$22) -> 200
A28: Rótulos de Linha | B28: Contagem de ID_Transacao
A29: Aguardando | B29: 346
A30: Em Rota | B30: 317
A31: Entregue | B31: 357
A32: Total Geral | B32: 1020
A35: =IF(CALCULUS!$A$11="Saida","Monitoramento de Pedidos e Entregas (Saídas)", IF(CALCULUS!$A$11="Entrada", "Monitoramento de Pedidos e Entregas (Entradas)","Monitoramento de Pedidos e Entregas (Total)")) -> Monitoramento de Pedidos e Entregas (Total)

Sheet DASHBOARD
